{
  "geradoEm": "2026-05-25T05:37:06.962Z",
  "entrada": {
    "filmesXtream": 29214,
    "seriesXtream": 7427,
    "canaisXtream": 1872
  },
  "saida": {
    "filmesFinais": 16829,
    "seriesFinais": 7172,
    "canaisFinais": 1771
  },
  "semLimite": {
    "filmesAgrupados": 16829,
    "seriesAgrupadas": 7172,
    "canais": 1771
  },
  "filtros": {
    "filmesBloqueados": 3902,
    "seriesBloqueadas": 0,
    "canaisBloqueados": 101
  },
  "agrupamento": {
    "limiteFilmesAtivo": false,
    "filmesAgrupadosComoDuplicados": 8483,
    "filmesComMaisDeUmaOpcao": 7140
  },
  "episodios": {
    "totalEpisodios": 229572,
    "seriesSemEpisodios": 0
  },
  "capas": {
    "filmesSemCapa": 220,
    "filmesSemBanner": 965,
    "seriesSemCapa": 109,
    "seriesSemBanner": 171,
    "canaisSemCapa": 0
  },
  "tmdb": {
    "filmesNaoEncontrados": 429,
    "seriesNaoEncontradas": 137
  }
}