{
  "id": "a-crise-dos-caras",
  "tipo": "serie",
  "titulo": "A Crise dos Caras",
  "ano": null,
  "descricao": "Quatro amigos quarentões fazem o que podem para encarar a masculinidade moderna, mas acabam metendo os pés pelas mãos.",
  "generos": [
    "NETFLIX"
  ],
  "capa": "https://image.tmdb.org/t/p/w500/hOq7UDe4W9g3K3NFHDCvzJVPih8.jpg",
  "banner": "https://image.tmdb.org/t/p/original/l1fYY1YpDHL0GsC5pz0IP9E6ivC.jpg",
  "tmdbId": 298699,
  "nota": 6.2,
  "xtreamSeriesId": 3965,
  "temporadas": [
    {
      "numero": 1,
      "nome": "Temporada 1",
      "episodios": [
        {
          "id": "ep-10899507",
          "tipo": "episodio",
          "titulo": "A Crise dos Caras S01E01",
          "numero": 1,
          "temporada": 1,
          "xtreamId": "10899507",
          "container": "mp4",
          "capa": "http://image.tmdb.org/t/p/w227_and_h127_bestv2/hOq7UDe4W9g3K3NFHDCvzJVPih8.jpg",
          "duracao": null,
          "descricao": ""
        },
        {
          "id": "ep-10899508",
          "tipo": "episodio",
          "titulo": "A Crise dos Caras S01E02",
          "numero": 2,
          "temporada": 1,
          "xtreamId": "10899508",
          "container": "mp4",
          "capa": "http://image.tmdb.org/t/p/w227_and_h127_bestv2/hOq7UDe4W9g3K3NFHDCvzJVPih8.jpg",
          "duracao": null,
          "descricao": ""
        },
        {
          "id": "ep-10899509",
          "tipo": "episodio",
          "titulo": "A Crise dos Caras S01E03",
          "numero": 3,
          "temporada": 1,
          "xtreamId": "10899509",
          "container": "mp4",
          "capa": "http://image.tmdb.org/t/p/w227_and_h127_bestv2/hOq7UDe4W9g3K3NFHDCvzJVPih8.jpg",
          "duracao": null,
          "descricao": ""
        },
        {
          "id": "ep-10899510",
          "tipo": "episodio",
          "titulo": "A Crise dos Caras S01E04",
          "numero": 4,
          "temporada": 1,
          "xtreamId": "10899510",
          "container": "mp4",
          "capa": "http://image.tmdb.org/t/p/w227_and_h127_bestv2/hOq7UDe4W9g3K3NFHDCvzJVPih8.jpg",
          "duracao": null,
          "descricao": ""
        },
        {
          "id": "ep-10899511",
          "tipo": "episodio",
          "titulo": "A Crise dos Caras S01E05",
          "numero": 5,
          "temporada": 1,
          "xtreamId": "10899511",
          "container": "mp4",
          "capa": "http://image.tmdb.org/t/p/w227_and_h127_bestv2/hOq7UDe4W9g3K3NFHDCvzJVPih8.jpg",
          "duracao": null,
          "descricao": ""
        },
        {
          "id": "ep-10899512",
          "tipo": "episodio",
          "titulo": "A Crise dos Caras S01E06",
          "numero": 6,
          "temporada": 1,
          "xtreamId": "10899512",
          "container": "mp4",
          "capa": "http://image.tmdb.org/t/p/w227_and_h127_bestv2/hOq7UDe4W9g3K3NFHDCvzJVPih8.jpg",
          "duracao": null,
          "descricao": ""
        },
        {
          "id": "ep-10899513",
          "tipo": "episodio",
          "titulo": "A Crise dos Caras S01E07",
          "numero": 7,
          "temporada": 1,
          "xtreamId": "10899513",
          "container": "mp4",
          "capa": "http://image.tmdb.org/t/p/w227_and_h127_bestv2/hOq7UDe4W9g3K3NFHDCvzJVPih8.jpg",
          "duracao": null,
          "descricao": ""
        },
        {
          "id": "ep-10899514",
          "tipo": "episodio",
          "titulo": "A Crise dos Caras S01E08",
          "numero": 8,
          "temporada": 1,
          "xtreamId": "10899514",
          "container": "mp4",
          "capa": "http://image.tmdb.org/t/p/w227_and_h127_bestv2/hOq7UDe4W9g3K3NFHDCvzJVPih8.jpg",
          "duracao": null,
          "descricao": ""
        }
      ]
    }
  ],
  "totalTemporadas": 1,
  "totalEpisodios": 8,
  "tituloOriginal": "Alphamännchen",
  "dataLancamento": "2025-10-02"
}