{
  "id": "a-franquia",
  "tipo": "serie",
  "titulo": "A Franquia",
  "ano": null,
  "descricao": "Nesta comédia da HBO, a equipe de uma saga de filmes de super-heróis pouco apreciada luta por um lugar no mundo selvagem do cinema.",
  "generos": [
    "HBO MAX"
  ],
  "capa": "https://image.tmdb.org/t/p/w500/2JqfBDYBWAsZ0DyZ4yxciih1JKD.jpg",
  "banner": "https://image.tmdb.org/t/p/original/5bkxQ4fXDMhfF8CAToNxmz0gC7O.jpg",
  "tmdbId": 216619,
  "nota": 6.52,
  "xtreamSeriesId": 3371,
  "temporadas": [
    {
      "numero": 1,
      "nome": "Temporada 1",
      "episodios": [
        {
          "id": "ep-10883010",
          "tipo": "episodio",
          "titulo": "A Franquia S01E01",
          "numero": 1,
          "temporada": 1,
          "xtreamId": "10883010",
          "container": "mp4",
          "capa": "http://image.tmdb.org/t/p/w227_and_h127_bestv2/2JqfBDYBWAsZ0DyZ4yxciih1JKD.jpg",
          "duracao": null,
          "descricao": ""
        },
        {
          "id": "ep-10883011",
          "tipo": "episodio",
          "titulo": "A Franquia S01E02",
          "numero": 2,
          "temporada": 1,
          "xtreamId": "10883011",
          "container": "mp4",
          "capa": "http://image.tmdb.org/t/p/w227_and_h127_bestv2/2JqfBDYBWAsZ0DyZ4yxciih1JKD.jpg",
          "duracao": null,
          "descricao": ""
        },
        {
          "id": "ep-10883012",
          "tipo": "episodio",
          "titulo": "A Franquia S01E03",
          "numero": 3,
          "temporada": 1,
          "xtreamId": "10883012",
          "container": "mp4",
          "capa": "http://image.tmdb.org/t/p/w227_and_h127_bestv2/2JqfBDYBWAsZ0DyZ4yxciih1JKD.jpg",
          "duracao": null,
          "descricao": ""
        },
        {
          "id": "ep-10883013",
          "tipo": "episodio",
          "titulo": "A Franquia S01E04",
          "numero": 4,
          "temporada": 1,
          "xtreamId": "10883013",
          "container": "mp4",
          "capa": "http://image.tmdb.org/t/p/w227_and_h127_bestv2/2JqfBDYBWAsZ0DyZ4yxciih1JKD.jpg",
          "duracao": null,
          "descricao": ""
        },
        {
          "id": "ep-10883014",
          "tipo": "episodio",
          "titulo": "A Franquia S01E05",
          "numero": 5,
          "temporada": 1,
          "xtreamId": "10883014",
          "container": "mp4",
          "capa": "http://image.tmdb.org/t/p/w227_and_h127_bestv2/2JqfBDYBWAsZ0DyZ4yxciih1JKD.jpg",
          "duracao": null,
          "descricao": ""
        },
        {
          "id": "ep-10883015",
          "tipo": "episodio",
          "titulo": "A Franquia S01E06",
          "numero": 6,
          "temporada": 1,
          "xtreamId": "10883015",
          "container": "mp4",
          "capa": "http://image.tmdb.org/t/p/w227_and_h127_bestv2/2JqfBDYBWAsZ0DyZ4yxciih1JKD.jpg",
          "duracao": null,
          "descricao": ""
        },
        {
          "id": "ep-10883016",
          "tipo": "episodio",
          "titulo": "A Franquia S01E07",
          "numero": 7,
          "temporada": 1,
          "xtreamId": "10883016",
          "container": "mp4",
          "capa": "http://image.tmdb.org/t/p/w227_and_h127_bestv2/2JqfBDYBWAsZ0DyZ4yxciih1JKD.jpg",
          "duracao": null,
          "descricao": ""
        },
        {
          "id": "ep-10883017",
          "tipo": "episodio",
          "titulo": "A Franquia S01E08",
          "numero": 8,
          "temporada": 1,
          "xtreamId": "10883017",
          "container": "mp4",
          "capa": "http://image.tmdb.org/t/p/w227_and_h127_bestv2/2JqfBDYBWAsZ0DyZ4yxciih1JKD.jpg",
          "duracao": null,
          "descricao": ""
        }
      ]
    }
  ],
  "totalTemporadas": 1,
  "totalEpisodios": 8,
  "tituloOriginal": "The Franchise",
  "dataLancamento": "2024-10-06"
}