{
  "id": "iludida-sadakatsiz",
  "tipo": "serie",
  "titulo": "Iludida",
  "ano": null,
  "descricao": "A história de amor entre Asya e Volkan parece ser perfeita, mas com um pequeno detalhe. Por um fio de cabelo, tudo pode terminar em vingança.",
  "generos": [
    "TURCAS | MEXICANAS"
  ],
  "capa": "https://image.tmdb.org/t/p/w500/xC9vUFVIrxnhZiEYLeMDVqxj7og.jpg",
  "banner": "https://image.tmdb.org/t/p/original/76aveobsWhFYon5DHP7CAjo9GYJ.jpg",
  "tmdbId": 110562,
  "nota": 8,
  "xtreamSeriesId": 7879,
  "temporadas": [
    {
      "numero": 1,
      "nome": "Temporada 1",
      "episodios": [
        {
          "id": "ep-11081255",
          "tipo": "episodio",
          "titulo": "Iludida - Sadakatsiz [DUB] S01E01",
          "numero": 1,
          "temporada": 1,
          "xtreamId": "11081255",
          "container": "mp4",
          "capa": "https://image.tmdb.org/t/p/w600_and_h900_bestv2/xC9vUFVIrxnhZiEYLeMDVqxj7og.jpg",
          "duracao": null,
          "descricao": "A história de amor entre Asya e Volkan parece ser perfeita, mas com um pequeno detalhe. Por um fio de cabelo, tudo pode terminar em vingança."
        },
        {
          "id": "ep-11081256",
          "tipo": "episodio",
          "titulo": "Iludida - Sadakatsiz [DUB] S01E02",
          "numero": 2,
          "temporada": 1,
          "xtreamId": "11081256",
          "container": "mp4",
          "capa": "https://image.tmdb.org/t/p/w600_and_h900_bestv2/xC9vUFVIrxnhZiEYLeMDVqxj7og.jpg",
          "duracao": null,
          "descricao": "A história de amor entre Asya e Volkan parece ser perfeita, mas com um pequeno detalhe. Por um fio de cabelo, tudo pode terminar em vingança."
        },
        {
          "id": "ep-11081257",
          "tipo": "episodio",
          "titulo": "Iludida - Sadakatsiz [DUB] S01E03",
          "numero": 3,
          "temporada": 1,
          "xtreamId": "11081257",
          "container": "mp4",
          "capa": "https://image.tmdb.org/t/p/w600_and_h900_bestv2/xC9vUFVIrxnhZiEYLeMDVqxj7og.jpg",
          "duracao": null,
          "descricao": "A história de amor entre Asya e Volkan parece ser perfeita, mas com um pequeno detalhe. Por um fio de cabelo, tudo pode terminar em vingança."
        },
        {
          "id": "ep-11081258",
          "tipo": "episodio",
          "titulo": "Iludida - Sadakatsiz [DUB] S01E04",
          "numero": 4,
          "temporada": 1,
          "xtreamId": "11081258",
          "container": "mp4",
          "capa": "https://image.tmdb.org/t/p/w600_and_h900_bestv2/xC9vUFVIrxnhZiEYLeMDVqxj7og.jpg",
          "duracao": null,
          "descricao": "A história de amor entre Asya e Volkan parece ser perfeita, mas com um pequeno detalhe. Por um fio de cabelo, tudo pode terminar em vingança."
        },
        {
          "id": "ep-11081259",
          "tipo": "episodio",
          "titulo": "Iludida - Sadakatsiz [DUB] S01E05",
          "numero": 5,
          "temporada": 1,
          "xtreamId": "11081259",
          "container": "mp4",
          "capa": "https://image.tmdb.org/t/p/w600_and_h900_bestv2/xC9vUFVIrxnhZiEYLeMDVqxj7og.jpg",
          "duracao": null,
          "descricao": "A história de amor entre Asya e Volkan parece ser perfeita, mas com um pequeno detalhe. Por um fio de cabelo, tudo pode terminar em vingança."
        },
        {
          "id": "ep-11081260",
          "tipo": "episodio",
          "titulo": "Iludida - Sadakatsiz [DUB] S01E06",
          "numero": 6,
          "temporada": 1,
          "xtreamId": "11081260",
          "container": "mp4",
          "capa": "https://image.tmdb.org/t/p/w600_and_h900_bestv2/xC9vUFVIrxnhZiEYLeMDVqxj7og.jpg",
          "duracao": null,
          "descricao": "A história de amor entre Asya e Volkan parece ser perfeita, mas com um pequeno detalhe. Por um fio de cabelo, tudo pode terminar em vingança."
        },
        {
          "id": "ep-11081261",
          "tipo": "episodio",
          "titulo": "Iludida - Sadakatsiz [DUB] S01E07",
          "numero": 7,
          "temporada": 1,
          "xtreamId": "11081261",
          "container": "mp4",
          "capa": "https://image.tmdb.org/t/p/w600_and_h900_bestv2/xC9vUFVIrxnhZiEYLeMDVqxj7og.jpg",
          "duracao": null,
          "descricao": "A história de amor entre Asya e Volkan parece ser perfeita, mas com um pequeno detalhe. Por um fio de cabelo, tudo pode terminar em vingança."
        },
        {
          "id": "ep-11081262",
          "tipo": "episodio",
          "titulo": "Iludida - Sadakatsiz [DUB] S01E08",
          "numero": 8,
          "temporada": 1,
          "xtreamId": "11081262",
          "container": "mp4",
          "capa": "https://image.tmdb.org/t/p/w600_and_h900_bestv2/xC9vUFVIrxnhZiEYLeMDVqxj7og.jpg",
          "duracao": null,
          "descricao": "A história de amor entre Asya e Volkan parece ser perfeita, mas com um pequeno detalhe. Por um fio de cabelo, tudo pode terminar em vingança."
        },
        {
          "id": "ep-11081263",
          "tipo": "episodio",
          "titulo": "Iludida - Sadakatsiz [DUB] S01E09",
          "numero": 9,
          "temporada": 1,
          "xtreamId": "11081263",
          "container": "mp4",
          "capa": "https://image.tmdb.org/t/p/w600_and_h900_bestv2/xC9vUFVIrxnhZiEYLeMDVqxj7og.jpg",
          "duracao": null,
          "descricao": "A história de amor entre Asya e Volkan parece ser perfeita, mas com um pequeno detalhe. Por um fio de cabelo, tudo pode terminar em vingança."
        },
        {
          "id": "ep-11081264",
          "tipo": "episodio",
          "titulo": "Iludida - Sadakatsiz [DUB] S01E10",
          "numero": 10,
          "temporada": 1,
          "xtreamId": "11081264",
          "container": "mp4",
          "capa": "https://image.tmdb.org/t/p/w600_and_h900_bestv2/xC9vUFVIrxnhZiEYLeMDVqxj7og.jpg",
          "duracao": null,
          "descricao": "A história de amor entre Asya e Volkan parece ser perfeita, mas com um pequeno detalhe. Por um fio de cabelo, tudo pode terminar em vingança."
        },
        {
          "id": "ep-11081265",
          "tipo": "episodio",
          "titulo": "Iludida - Sadakatsiz [DUB] S01E11",
          "numero": 11,
          "temporada": 1,
          "xtreamId": "11081265",
          "container": "mp4",
          "capa": "https://image.tmdb.org/t/p/w600_and_h900_bestv2/xC9vUFVIrxnhZiEYLeMDVqxj7og.jpg",
          "duracao": null,
          "descricao": "A história de amor entre Asya e Volkan parece ser perfeita, mas com um pequeno detalhe. Por um fio de cabelo, tudo pode terminar em vingança."
        },
        {
          "id": "ep-11081266",
          "tipo": "episodio",
          "titulo": "Iludida - Sadakatsiz [DUB] S01E12",
          "numero": 12,
          "temporada": 1,
          "xtreamId": "11081266",
          "container": "mp4",
          "capa": "https://image.tmdb.org/t/p/w600_and_h900_bestv2/xC9vUFVIrxnhZiEYLeMDVqxj7og.jpg",
          "duracao": null,
          "descricao": "A história de amor entre Asya e Volkan parece ser perfeita, mas com um pequeno detalhe. Por um fio de cabelo, tudo pode terminar em vingança."
        },
        {
          "id": "ep-11081267",
          "tipo": "episodio",
          "titulo": "Iludida - Sadakatsiz [DUB] S01E13",
          "numero": 13,
          "temporada": 1,
          "xtreamId": "11081267",
          "container": "mp4",
          "capa": "https://image.tmdb.org/t/p/w600_and_h900_bestv2/xC9vUFVIrxnhZiEYLeMDVqxj7og.jpg",
          "duracao": null,
          "descricao": "A história de amor entre Asya e Volkan parece ser perfeita, mas com um pequeno detalhe. Por um fio de cabelo, tudo pode terminar em vingança."
        },
        {
          "id": "ep-11081268",
          "tipo": "episodio",
          "titulo": "Iludida - Sadakatsiz [DUB] S01E14",
          "numero": 14,
          "temporada": 1,
          "xtreamId": "11081268",
          "container": "mp4",
          "capa": "https://image.tmdb.org/t/p/w600_and_h900_bestv2/xC9vUFVIrxnhZiEYLeMDVqxj7og.jpg",
          "duracao": null,
          "descricao": "A história de amor entre Asya e Volkan parece ser perfeita, mas com um pequeno detalhe. Por um fio de cabelo, tudo pode terminar em vingança."
        },
        {
          "id": "ep-11081269",
          "tipo": "episodio",
          "titulo": "Iludida - Sadakatsiz [DUB] S01E15",
          "numero": 15,
          "temporada": 1,
          "xtreamId": "11081269",
          "container": "mp4",
          "capa": "https://image.tmdb.org/t/p/w600_and_h900_bestv2/xC9vUFVIrxnhZiEYLeMDVqxj7og.jpg",
          "duracao": null,
          "descricao": "A história de amor entre Asya e Volkan parece ser perfeita, mas com um pequeno detalhe. Por um fio de cabelo, tudo pode terminar em vingança."
        },
        {
          "id": "ep-11081270",
          "tipo": "episodio",
          "titulo": "Iludida - Sadakatsiz [DUB] S01E16",
          "numero": 16,
          "temporada": 1,
          "xtreamId": "11081270",
          "container": "mp4",
          "capa": "https://image.tmdb.org/t/p/w600_and_h900_bestv2/xC9vUFVIrxnhZiEYLeMDVqxj7og.jpg",
          "duracao": null,
          "descricao": "A história de amor entre Asya e Volkan parece ser perfeita, mas com um pequeno detalhe. Por um fio de cabelo, tudo pode terminar em vingança."
        },
        {
          "id": "ep-11081271",
          "tipo": "episodio",
          "titulo": "Iludida - Sadakatsiz [DUB] S01E17",
          "numero": 17,
          "temporada": 1,
          "xtreamId": "11081271",
          "container": "mp4",
          "capa": "https://image.tmdb.org/t/p/w600_and_h900_bestv2/xC9vUFVIrxnhZiEYLeMDVqxj7og.jpg",
          "duracao": null,
          "descricao": "A história de amor entre Asya e Volkan parece ser perfeita, mas com um pequeno detalhe. Por um fio de cabelo, tudo pode terminar em vingança."
        },
        {
          "id": "ep-11081272",
          "tipo": "episodio",
          "titulo": "Iludida - Sadakatsiz [DUB] S01E18",
          "numero": 18,
          "temporada": 1,
          "xtreamId": "11081272",
          "container": "mp4",
          "capa": "https://image.tmdb.org/t/p/w600_and_h900_bestv2/xC9vUFVIrxnhZiEYLeMDVqxj7og.jpg",
          "duracao": null,
          "descricao": "A história de amor entre Asya e Volkan parece ser perfeita, mas com um pequeno detalhe. Por um fio de cabelo, tudo pode terminar em vingança."
        },
        {
          "id": "ep-11081273",
          "tipo": "episodio",
          "titulo": "Iludida - Sadakatsiz [DUB] S01E19",
          "numero": 19,
          "temporada": 1,
          "xtreamId": "11081273",
          "container": "mp4",
          "capa": "https://image.tmdb.org/t/p/w600_and_h900_bestv2/xC9vUFVIrxnhZiEYLeMDVqxj7og.jpg",
          "duracao": null,
          "descricao": "A história de amor entre Asya e Volkan parece ser perfeita, mas com um pequeno detalhe. Por um fio de cabelo, tudo pode terminar em vingança."
        },
        {
          "id": "ep-11081274",
          "tipo": "episodio",
          "titulo": "Iludida - Sadakatsiz [DUB] S01E20",
          "numero": 20,
          "temporada": 1,
          "xtreamId": "11081274",
          "container": "mp4",
          "capa": "https://image.tmdb.org/t/p/w600_and_h900_bestv2/xC9vUFVIrxnhZiEYLeMDVqxj7og.jpg",
          "duracao": null,
          "descricao": "A história de amor entre Asya e Volkan parece ser perfeita, mas com um pequeno detalhe. Por um fio de cabelo, tudo pode terminar em vingança."
        },
        {
          "id": "ep-11081275",
          "tipo": "episodio",
          "titulo": "Iludida - Sadakatsiz [DUB] S01E21",
          "numero": 21,
          "temporada": 1,
          "xtreamId": "11081275",
          "container": "mp4",
          "capa": "https://image.tmdb.org/t/p/w600_and_h900_bestv2/xC9vUFVIrxnhZiEYLeMDVqxj7og.jpg",
          "duracao": null,
          "descricao": "A história de amor entre Asya e Volkan parece ser perfeita, mas com um pequeno detalhe. Por um fio de cabelo, tudo pode terminar em vingança."
        },
        {
          "id": "ep-11081276",
          "tipo": "episodio",
          "titulo": "Iludida - Sadakatsiz [DUB] S01E22",
          "numero": 22,
          "temporada": 1,
          "xtreamId": "11081276",
          "container": "mp4",
          "capa": "https://image.tmdb.org/t/p/w600_and_h900_bestv2/xC9vUFVIrxnhZiEYLeMDVqxj7og.jpg",
          "duracao": null,
          "descricao": "A história de amor entre Asya e Volkan parece ser perfeita, mas com um pequeno detalhe. Por um fio de cabelo, tudo pode terminar em vingança."
        },
        {
          "id": "ep-11081277",
          "tipo": "episodio",
          "titulo": "Iludida - Sadakatsiz [DUB] S01E23",
          "numero": 23,
          "temporada": 1,
          "xtreamId": "11081277",
          "container": "mp4",
          "capa": "https://image.tmdb.org/t/p/w600_and_h900_bestv2/xC9vUFVIrxnhZiEYLeMDVqxj7og.jpg",
          "duracao": null,
          "descricao": "A história de amor entre Asya e Volkan parece ser perfeita, mas com um pequeno detalhe. Por um fio de cabelo, tudo pode terminar em vingança."
        },
        {
          "id": "ep-11081278",
          "tipo": "episodio",
          "titulo": "Iludida - Sadakatsiz [DUB] S01E24",
          "numero": 24,
          "temporada": 1,
          "xtreamId": "11081278",
          "container": "mp4",
          "capa": "https://image.tmdb.org/t/p/w600_and_h900_bestv2/xC9vUFVIrxnhZiEYLeMDVqxj7og.jpg",
          "duracao": null,
          "descricao": "A história de amor entre Asya e Volkan parece ser perfeita, mas com um pequeno detalhe. Por um fio de cabelo, tudo pode terminar em vingança."
        },
        {
          "id": "ep-11081279",
          "tipo": "episodio",
          "titulo": "Iludida - Sadakatsiz [DUB] S01E25",
          "numero": 25,
          "temporada": 1,
          "xtreamId": "11081279",
          "container": "mp4",
          "capa": "https://image.tmdb.org/t/p/w600_and_h900_bestv2/xC9vUFVIrxnhZiEYLeMDVqxj7og.jpg",
          "duracao": null,
          "descricao": "A história de amor entre Asya e Volkan parece ser perfeita, mas com um pequeno detalhe. Por um fio de cabelo, tudo pode terminar em vingança."
        },
        {
          "id": "ep-11081280",
          "tipo": "episodio",
          "titulo": "Iludida - Sadakatsiz [DUB] S01E26",
          "numero": 26,
          "temporada": 1,
          "xtreamId": "11081280",
          "container": "mp4",
          "capa": "https://image.tmdb.org/t/p/w600_and_h900_bestv2/xC9vUFVIrxnhZiEYLeMDVqxj7og.jpg",
          "duracao": null,
          "descricao": "A história de amor entre Asya e Volkan parece ser perfeita, mas com um pequeno detalhe. Por um fio de cabelo, tudo pode terminar em vingança."
        },
        {
          "id": "ep-11081281",
          "tipo": "episodio",
          "titulo": "Iludida - Sadakatsiz [DUB] S01E27",
          "numero": 27,
          "temporada": 1,
          "xtreamId": "11081281",
          "container": "mp4",
          "capa": "https://image.tmdb.org/t/p/w600_and_h900_bestv2/xC9vUFVIrxnhZiEYLeMDVqxj7og.jpg",
          "duracao": null,
          "descricao": "A história de amor entre Asya e Volkan parece ser perfeita, mas com um pequeno detalhe. Por um fio de cabelo, tudo pode terminar em vingança."
        },
        {
          "id": "ep-11081282",
          "tipo": "episodio",
          "titulo": "Iludida - Sadakatsiz [DUB] S01E28",
          "numero": 28,
          "temporada": 1,
          "xtreamId": "11081282",
          "container": "mp4",
          "capa": "https://image.tmdb.org/t/p/w600_and_h900_bestv2/xC9vUFVIrxnhZiEYLeMDVqxj7og.jpg",
          "duracao": null,
          "descricao": "A história de amor entre Asya e Volkan parece ser perfeita, mas com um pequeno detalhe. Por um fio de cabelo, tudo pode terminar em vingança."
        },
        {
          "id": "ep-11081283",
          "tipo": "episodio",
          "titulo": "Iludida - Sadakatsiz [DUB] S01E29",
          "numero": 29,
          "temporada": 1,
          "xtreamId": "11081283",
          "container": "mp4",
          "capa": "https://image.tmdb.org/t/p/w600_and_h900_bestv2/xC9vUFVIrxnhZiEYLeMDVqxj7og.jpg",
          "duracao": null,
          "descricao": "A história de amor entre Asya e Volkan parece ser perfeita, mas com um pequeno detalhe. Por um fio de cabelo, tudo pode terminar em vingança."
        },
        {
          "id": "ep-11081284",
          "tipo": "episodio",
          "titulo": "Iludida - Sadakatsiz [DUB] S01E30",
          "numero": 30,
          "temporada": 1,
          "xtreamId": "11081284",
          "container": "mp4",
          "capa": "https://image.tmdb.org/t/p/w600_and_h900_bestv2/xC9vUFVIrxnhZiEYLeMDVqxj7og.jpg",
          "duracao": null,
          "descricao": "A história de amor entre Asya e Volkan parece ser perfeita, mas com um pequeno detalhe. Por um fio de cabelo, tudo pode terminar em vingança."
        },
        {
          "id": "ep-11081285",
          "tipo": "episodio",
          "titulo": "Iludida - Sadakatsiz [DUB] S01E31",
          "numero": 31,
          "temporada": 1,
          "xtreamId": "11081285",
          "container": "mp4",
          "capa": "https://image.tmdb.org/t/p/w600_and_h900_bestv2/xC9vUFVIrxnhZiEYLeMDVqxj7og.jpg",
          "duracao": null,
          "descricao": "A história de amor entre Asya e Volkan parece ser perfeita, mas com um pequeno detalhe. Por um fio de cabelo, tudo pode terminar em vingança."
        },
        {
          "id": "ep-11081286",
          "tipo": "episodio",
          "titulo": "Iludida - Sadakatsiz [DUB] S01E32",
          "numero": 32,
          "temporada": 1,
          "xtreamId": "11081286",
          "container": "mp4",
          "capa": "https://image.tmdb.org/t/p/w600_and_h900_bestv2/xC9vUFVIrxnhZiEYLeMDVqxj7og.jpg",
          "duracao": null,
          "descricao": "A história de amor entre Asya e Volkan parece ser perfeita, mas com um pequeno detalhe. Por um fio de cabelo, tudo pode terminar em vingança."
        },
        {
          "id": "ep-11081287",
          "tipo": "episodio",
          "titulo": "Iludida - Sadakatsiz [DUB] S01E33",
          "numero": 33,
          "temporada": 1,
          "xtreamId": "11081287",
          "container": "mp4",
          "capa": "https://image.tmdb.org/t/p/w600_and_h900_bestv2/xC9vUFVIrxnhZiEYLeMDVqxj7og.jpg",
          "duracao": null,
          "descricao": "A história de amor entre Asya e Volkan parece ser perfeita, mas com um pequeno detalhe. Por um fio de cabelo, tudo pode terminar em vingança."
        },
        {
          "id": "ep-11081288",
          "tipo": "episodio",
          "titulo": "Iludida - Sadakatsiz [DUB] S01E34",
          "numero": 34,
          "temporada": 1,
          "xtreamId": "11081288",
          "container": "mp4",
          "capa": "https://image.tmdb.org/t/p/w600_and_h900_bestv2/xC9vUFVIrxnhZiEYLeMDVqxj7og.jpg",
          "duracao": null,
          "descricao": "A história de amor entre Asya e Volkan parece ser perfeita, mas com um pequeno detalhe. Por um fio de cabelo, tudo pode terminar em vingança."
        },
        {
          "id": "ep-11081289",
          "tipo": "episodio",
          "titulo": "Iludida - Sadakatsiz [DUB] S01E35",
          "numero": 35,
          "temporada": 1,
          "xtreamId": "11081289",
          "container": "mp4",
          "capa": "https://image.tmdb.org/t/p/w600_and_h900_bestv2/xC9vUFVIrxnhZiEYLeMDVqxj7og.jpg",
          "duracao": null,
          "descricao": "A história de amor entre Asya e Volkan parece ser perfeita, mas com um pequeno detalhe. Por um fio de cabelo, tudo pode terminar em vingança."
        },
        {
          "id": "ep-11081290",
          "tipo": "episodio",
          "titulo": "Iludida - Sadakatsiz [DUB] S01E36",
          "numero": 36,
          "temporada": 1,
          "xtreamId": "11081290",
          "container": "mp4",
          "capa": "https://image.tmdb.org/t/p/w600_and_h900_bestv2/xC9vUFVIrxnhZiEYLeMDVqxj7og.jpg",
          "duracao": null,
          "descricao": "A história de amor entre Asya e Volkan parece ser perfeita, mas com um pequeno detalhe. Por um fio de cabelo, tudo pode terminar em vingança."
        },
        {
          "id": "ep-11081291",
          "tipo": "episodio",
          "titulo": "Iludida - Sadakatsiz [DUB] S01E37",
          "numero": 37,
          "temporada": 1,
          "xtreamId": "11081291",
          "container": "mp4",
          "capa": "https://image.tmdb.org/t/p/w600_and_h900_bestv2/xC9vUFVIrxnhZiEYLeMDVqxj7og.jpg",
          "duracao": null,
          "descricao": "A história de amor entre Asya e Volkan parece ser perfeita, mas com um pequeno detalhe. Por um fio de cabelo, tudo pode terminar em vingança."
        },
        {
          "id": "ep-11081292",
          "tipo": "episodio",
          "titulo": "Iludida - Sadakatsiz [DUB] S01E38",
          "numero": 38,
          "temporada": 1,
          "xtreamId": "11081292",
          "container": "mp4",
          "capa": "https://image.tmdb.org/t/p/w600_and_h900_bestv2/xC9vUFVIrxnhZiEYLeMDVqxj7og.jpg",
          "duracao": null,
          "descricao": "A história de amor entre Asya e Volkan parece ser perfeita, mas com um pequeno detalhe. Por um fio de cabelo, tudo pode terminar em vingança."
        },
        {
          "id": "ep-11081293",
          "tipo": "episodio",
          "titulo": "Iludida - Sadakatsiz [DUB] S01E39",
          "numero": 39,
          "temporada": 1,
          "xtreamId": "11081293",
          "container": "mp4",
          "capa": "https://image.tmdb.org/t/p/w600_and_h900_bestv2/xC9vUFVIrxnhZiEYLeMDVqxj7og.jpg",
          "duracao": null,
          "descricao": "A história de amor entre Asya e Volkan parece ser perfeita, mas com um pequeno detalhe. Por um fio de cabelo, tudo pode terminar em vingança."
        },
        {
          "id": "ep-11081294",
          "tipo": "episodio",
          "titulo": "Iludida - Sadakatsiz [DUB] S01E40",
          "numero": 40,
          "temporada": 1,
          "xtreamId": "11081294",
          "container": "mp4",
          "capa": "https://image.tmdb.org/t/p/w600_and_h900_bestv2/xC9vUFVIrxnhZiEYLeMDVqxj7og.jpg",
          "duracao": null,
          "descricao": "A história de amor entre Asya e Volkan parece ser perfeita, mas com um pequeno detalhe. Por um fio de cabelo, tudo pode terminar em vingança."
        },
        {
          "id": "ep-11081295",
          "tipo": "episodio",
          "titulo": "Iludida - Sadakatsiz [DUB] S01E41",
          "numero": 41,
          "temporada": 1,
          "xtreamId": "11081295",
          "container": "mp4",
          "capa": "https://image.tmdb.org/t/p/w600_and_h900_bestv2/xC9vUFVIrxnhZiEYLeMDVqxj7og.jpg",
          "duracao": null,
          "descricao": "A história de amor entre Asya e Volkan parece ser perfeita, mas com um pequeno detalhe. Por um fio de cabelo, tudo pode terminar em vingança."
        },
        {
          "id": "ep-11081296",
          "tipo": "episodio",
          "titulo": "Iludida - Sadakatsiz [DUB] S01E42",
          "numero": 42,
          "temporada": 1,
          "xtreamId": "11081296",
          "container": "mp4",
          "capa": "https://image.tmdb.org/t/p/w600_and_h900_bestv2/xC9vUFVIrxnhZiEYLeMDVqxj7og.jpg",
          "duracao": null,
          "descricao": "A história de amor entre Asya e Volkan parece ser perfeita, mas com um pequeno detalhe. Por um fio de cabelo, tudo pode terminar em vingança."
        },
        {
          "id": "ep-11081297",
          "tipo": "episodio",
          "titulo": "Iludida - Sadakatsiz [DUB] S01E43",
          "numero": 43,
          "temporada": 1,
          "xtreamId": "11081297",
          "container": "mp4",
          "capa": "https://image.tmdb.org/t/p/w600_and_h900_bestv2/xC9vUFVIrxnhZiEYLeMDVqxj7og.jpg",
          "duracao": null,
          "descricao": "A história de amor entre Asya e Volkan parece ser perfeita, mas com um pequeno detalhe. Por um fio de cabelo, tudo pode terminar em vingança."
        },
        {
          "id": "ep-11081298",
          "tipo": "episodio",
          "titulo": "Iludida - Sadakatsiz [DUB] S01E44",
          "numero": 44,
          "temporada": 1,
          "xtreamId": "11081298",
          "container": "mp4",
          "capa": "https://image.tmdb.org/t/p/w600_and_h900_bestv2/xC9vUFVIrxnhZiEYLeMDVqxj7og.jpg",
          "duracao": null,
          "descricao": "A história de amor entre Asya e Volkan parece ser perfeita, mas com um pequeno detalhe. Por um fio de cabelo, tudo pode terminar em vingança."
        },
        {
          "id": "ep-11081299",
          "tipo": "episodio",
          "titulo": "Iludida - Sadakatsiz [DUB] S01E45",
          "numero": 45,
          "temporada": 1,
          "xtreamId": "11081299",
          "container": "mp4",
          "capa": "https://image.tmdb.org/t/p/w600_and_h900_bestv2/xC9vUFVIrxnhZiEYLeMDVqxj7og.jpg",
          "duracao": null,
          "descricao": "A história de amor entre Asya e Volkan parece ser perfeita, mas com um pequeno detalhe. Por um fio de cabelo, tudo pode terminar em vingança."
        },
        {
          "id": "ep-11081300",
          "tipo": "episodio",
          "titulo": "Iludida - Sadakatsiz [DUB] S01E46",
          "numero": 46,
          "temporada": 1,
          "xtreamId": "11081300",
          "container": "mp4",
          "capa": "https://image.tmdb.org/t/p/w600_and_h900_bestv2/xC9vUFVIrxnhZiEYLeMDVqxj7og.jpg",
          "duracao": null,
          "descricao": "A história de amor entre Asya e Volkan parece ser perfeita, mas com um pequeno detalhe. Por um fio de cabelo, tudo pode terminar em vingança."
        },
        {
          "id": "ep-11081301",
          "tipo": "episodio",
          "titulo": "Iludida - Sadakatsiz [DUB] S01E47",
          "numero": 47,
          "temporada": 1,
          "xtreamId": "11081301",
          "container": "mp4",
          "capa": "https://image.tmdb.org/t/p/w600_and_h900_bestv2/xC9vUFVIrxnhZiEYLeMDVqxj7og.jpg",
          "duracao": null,
          "descricao": "A história de amor entre Asya e Volkan parece ser perfeita, mas com um pequeno detalhe. Por um fio de cabelo, tudo pode terminar em vingança."
        },
        {
          "id": "ep-11081302",
          "tipo": "episodio",
          "titulo": "Iludida - Sadakatsiz [DUB] S01E48",
          "numero": 48,
          "temporada": 1,
          "xtreamId": "11081302",
          "container": "mp4",
          "capa": "https://image.tmdb.org/t/p/w600_and_h900_bestv2/xC9vUFVIrxnhZiEYLeMDVqxj7og.jpg",
          "duracao": null,
          "descricao": "A história de amor entre Asya e Volkan parece ser perfeita, mas com um pequeno detalhe. Por um fio de cabelo, tudo pode terminar em vingança."
        },
        {
          "id": "ep-11081303",
          "tipo": "episodio",
          "titulo": "Iludida - Sadakatsiz [DUB] S01E49",
          "numero": 49,
          "temporada": 1,
          "xtreamId": "11081303",
          "container": "mp4",
          "capa": "https://image.tmdb.org/t/p/w600_and_h900_bestv2/xC9vUFVIrxnhZiEYLeMDVqxj7og.jpg",
          "duracao": null,
          "descricao": "A história de amor entre Asya e Volkan parece ser perfeita, mas com um pequeno detalhe. Por um fio de cabelo, tudo pode terminar em vingança."
        },
        {
          "id": "ep-11081304",
          "tipo": "episodio",
          "titulo": "Iludida - Sadakatsiz [DUB] S01E50",
          "numero": 50,
          "temporada": 1,
          "xtreamId": "11081304",
          "container": "mp4",
          "capa": "https://image.tmdb.org/t/p/w600_and_h900_bestv2/xC9vUFVIrxnhZiEYLeMDVqxj7og.jpg",
          "duracao": null,
          "descricao": "A história de amor entre Asya e Volkan parece ser perfeita, mas com um pequeno detalhe. Por um fio de cabelo, tudo pode terminar em vingança."
        },
        {
          "id": "ep-11081305",
          "tipo": "episodio",
          "titulo": "Iludida - Sadakatsiz [DUB] S01E51",
          "numero": 51,
          "temporada": 1,
          "xtreamId": "11081305",
          "container": "mp4",
          "capa": "https://image.tmdb.org/t/p/w600_and_h900_bestv2/xC9vUFVIrxnhZiEYLeMDVqxj7og.jpg",
          "duracao": null,
          "descricao": "A história de amor entre Asya e Volkan parece ser perfeita, mas com um pequeno detalhe. Por um fio de cabelo, tudo pode terminar em vingança."
        },
        {
          "id": "ep-11081306",
          "tipo": "episodio",
          "titulo": "Iludida - Sadakatsiz [DUB] S01E52",
          "numero": 52,
          "temporada": 1,
          "xtreamId": "11081306",
          "container": "mp4",
          "capa": "https://image.tmdb.org/t/p/w600_and_h900_bestv2/xC9vUFVIrxnhZiEYLeMDVqxj7og.jpg",
          "duracao": null,
          "descricao": "A história de amor entre Asya e Volkan parece ser perfeita, mas com um pequeno detalhe. Por um fio de cabelo, tudo pode terminar em vingança."
        },
        {
          "id": "ep-11081307",
          "tipo": "episodio",
          "titulo": "Iludida - Sadakatsiz [DUB] S01E53",
          "numero": 53,
          "temporada": 1,
          "xtreamId": "11081307",
          "container": "mp4",
          "capa": "https://image.tmdb.org/t/p/w600_and_h900_bestv2/xC9vUFVIrxnhZiEYLeMDVqxj7og.jpg",
          "duracao": null,
          "descricao": "A história de amor entre Asya e Volkan parece ser perfeita, mas com um pequeno detalhe. Por um fio de cabelo, tudo pode terminar em vingança."
        },
        {
          "id": "ep-11081308",
          "tipo": "episodio",
          "titulo": "Iludida - Sadakatsiz [DUB] S01E54",
          "numero": 54,
          "temporada": 1,
          "xtreamId": "11081308",
          "container": "mp4",
          "capa": "https://image.tmdb.org/t/p/w600_and_h900_bestv2/xC9vUFVIrxnhZiEYLeMDVqxj7og.jpg",
          "duracao": null,
          "descricao": "A história de amor entre Asya e Volkan parece ser perfeita, mas com um pequeno detalhe. Por um fio de cabelo, tudo pode terminar em vingança."
        },
        {
          "id": "ep-11081309",
          "tipo": "episodio",
          "titulo": "Iludida - Sadakatsiz [DUB] S01E55",
          "numero": 55,
          "temporada": 1,
          "xtreamId": "11081309",
          "container": "mp4",
          "capa": "https://image.tmdb.org/t/p/w600_and_h900_bestv2/xC9vUFVIrxnhZiEYLeMDVqxj7og.jpg",
          "duracao": null,
          "descricao": "A história de amor entre Asya e Volkan parece ser perfeita, mas com um pequeno detalhe. Por um fio de cabelo, tudo pode terminar em vingança."
        },
        {
          "id": "ep-11081310",
          "tipo": "episodio",
          "titulo": "Iludida - Sadakatsiz [DUB] S01E56",
          "numero": 56,
          "temporada": 1,
          "xtreamId": "11081310",
          "container": "mp4",
          "capa": "https://image.tmdb.org/t/p/w600_and_h900_bestv2/xC9vUFVIrxnhZiEYLeMDVqxj7og.jpg",
          "duracao": null,
          "descricao": "A história de amor entre Asya e Volkan parece ser perfeita, mas com um pequeno detalhe. Por um fio de cabelo, tudo pode terminar em vingança."
        },
        {
          "id": "ep-11081311",
          "tipo": "episodio",
          "titulo": "Iludida - Sadakatsiz [DUB] S01E57",
          "numero": 57,
          "temporada": 1,
          "xtreamId": "11081311",
          "container": "mp4",
          "capa": "https://image.tmdb.org/t/p/w600_and_h900_bestv2/xC9vUFVIrxnhZiEYLeMDVqxj7og.jpg",
          "duracao": null,
          "descricao": "A história de amor entre Asya e Volkan parece ser perfeita, mas com um pequeno detalhe. Por um fio de cabelo, tudo pode terminar em vingança."
        },
        {
          "id": "ep-11081312",
          "tipo": "episodio",
          "titulo": "Iludida - Sadakatsiz [DUB] S01E58",
          "numero": 58,
          "temporada": 1,
          "xtreamId": "11081312",
          "container": "mp4",
          "capa": "https://image.tmdb.org/t/p/w600_and_h900_bestv2/xC9vUFVIrxnhZiEYLeMDVqxj7og.jpg",
          "duracao": null,
          "descricao": "A história de amor entre Asya e Volkan parece ser perfeita, mas com um pequeno detalhe. Por um fio de cabelo, tudo pode terminar em vingança."
        },
        {
          "id": "ep-11081313",
          "tipo": "episodio",
          "titulo": "Iludida - Sadakatsiz [DUB] S01E59",
          "numero": 59,
          "temporada": 1,
          "xtreamId": "11081313",
          "container": "mp4",
          "capa": "https://image.tmdb.org/t/p/w600_and_h900_bestv2/xC9vUFVIrxnhZiEYLeMDVqxj7og.jpg",
          "duracao": null,
          "descricao": "A história de amor entre Asya e Volkan parece ser perfeita, mas com um pequeno detalhe. Por um fio de cabelo, tudo pode terminar em vingança."
        },
        {
          "id": "ep-11081314",
          "tipo": "episodio",
          "titulo": "Iludida - Sadakatsiz [DUB] S01E60",
          "numero": 60,
          "temporada": 1,
          "xtreamId": "11081314",
          "container": "mp4",
          "capa": "https://image.tmdb.org/t/p/w600_and_h900_bestv2/xC9vUFVIrxnhZiEYLeMDVqxj7og.jpg",
          "duracao": null,
          "descricao": "A história de amor entre Asya e Volkan parece ser perfeita, mas com um pequeno detalhe. Por um fio de cabelo, tudo pode terminar em vingança."
        },
        {
          "id": "ep-11081315",
          "tipo": "episodio",
          "titulo": "Iludida - Sadakatsiz [DUB] S01E61",
          "numero": 61,
          "temporada": 1,
          "xtreamId": "11081315",
          "container": "mp4",
          "capa": "https://image.tmdb.org/t/p/w600_and_h900_bestv2/xC9vUFVIrxnhZiEYLeMDVqxj7og.jpg",
          "duracao": null,
          "descricao": "A história de amor entre Asya e Volkan parece ser perfeita, mas com um pequeno detalhe. Por um fio de cabelo, tudo pode terminar em vingança."
        },
        {
          "id": "ep-11081316",
          "tipo": "episodio",
          "titulo": "Iludida - Sadakatsiz [DUB] S01E62",
          "numero": 62,
          "temporada": 1,
          "xtreamId": "11081316",
          "container": "mp4",
          "capa": "https://image.tmdb.org/t/p/w600_and_h900_bestv2/xC9vUFVIrxnhZiEYLeMDVqxj7og.jpg",
          "duracao": null,
          "descricao": "A história de amor entre Asya e Volkan parece ser perfeita, mas com um pequeno detalhe. Por um fio de cabelo, tudo pode terminar em vingança."
        },
        {
          "id": "ep-11081317",
          "tipo": "episodio",
          "titulo": "Iludida - Sadakatsiz [DUB] S01E63",
          "numero": 63,
          "temporada": 1,
          "xtreamId": "11081317",
          "container": "mp4",
          "capa": "https://image.tmdb.org/t/p/w600_and_h900_bestv2/xC9vUFVIrxnhZiEYLeMDVqxj7og.jpg",
          "duracao": null,
          "descricao": "A história de amor entre Asya e Volkan parece ser perfeita, mas com um pequeno detalhe. Por um fio de cabelo, tudo pode terminar em vingança."
        },
        {
          "id": "ep-11081318",
          "tipo": "episodio",
          "titulo": "Iludida - Sadakatsiz [DUB] S01E64",
          "numero": 64,
          "temporada": 1,
          "xtreamId": "11081318",
          "container": "mp4",
          "capa": "https://image.tmdb.org/t/p/w600_and_h900_bestv2/xC9vUFVIrxnhZiEYLeMDVqxj7og.jpg",
          "duracao": null,
          "descricao": "A história de amor entre Asya e Volkan parece ser perfeita, mas com um pequeno detalhe. Por um fio de cabelo, tudo pode terminar em vingança."
        },
        {
          "id": "ep-11081319",
          "tipo": "episodio",
          "titulo": "Iludida - Sadakatsiz [DUB] S01E65",
          "numero": 65,
          "temporada": 1,
          "xtreamId": "11081319",
          "container": "mp4",
          "capa": "https://image.tmdb.org/t/p/w600_and_h900_bestv2/xC9vUFVIrxnhZiEYLeMDVqxj7og.jpg",
          "duracao": null,
          "descricao": "A história de amor entre Asya e Volkan parece ser perfeita, mas com um pequeno detalhe. Por um fio de cabelo, tudo pode terminar em vingança."
        },
        {
          "id": "ep-11081320",
          "tipo": "episodio",
          "titulo": "Iludida - Sadakatsiz [DUB] S01E66",
          "numero": 66,
          "temporada": 1,
          "xtreamId": "11081320",
          "container": "mp4",
          "capa": "https://image.tmdb.org/t/p/w600_and_h900_bestv2/xC9vUFVIrxnhZiEYLeMDVqxj7og.jpg",
          "duracao": null,
          "descricao": "A história de amor entre Asya e Volkan parece ser perfeita, mas com um pequeno detalhe. Por um fio de cabelo, tudo pode terminar em vingança."
        },
        {
          "id": "ep-11081321",
          "tipo": "episodio",
          "titulo": "Iludida - Sadakatsiz [DUB] S01E67",
          "numero": 67,
          "temporada": 1,
          "xtreamId": "11081321",
          "container": "mp4",
          "capa": "https://image.tmdb.org/t/p/w600_and_h900_bestv2/xC9vUFVIrxnhZiEYLeMDVqxj7og.jpg",
          "duracao": null,
          "descricao": "A história de amor entre Asya e Volkan parece ser perfeita, mas com um pequeno detalhe. Por um fio de cabelo, tudo pode terminar em vingança."
        },
        {
          "id": "ep-11081322",
          "tipo": "episodio",
          "titulo": "Iludida - Sadakatsiz [DUB] S01E68",
          "numero": 68,
          "temporada": 1,
          "xtreamId": "11081322",
          "container": "mp4",
          "capa": "https://image.tmdb.org/t/p/w600_and_h900_bestv2/xC9vUFVIrxnhZiEYLeMDVqxj7og.jpg",
          "duracao": null,
          "descricao": "A história de amor entre Asya e Volkan parece ser perfeita, mas com um pequeno detalhe. Por um fio de cabelo, tudo pode terminar em vingança."
        },
        {
          "id": "ep-11081323",
          "tipo": "episodio",
          "titulo": "Iludida - Sadakatsiz [DUB] S01E69",
          "numero": 69,
          "temporada": 1,
          "xtreamId": "11081323",
          "container": "mp4",
          "capa": "https://image.tmdb.org/t/p/w600_and_h900_bestv2/xC9vUFVIrxnhZiEYLeMDVqxj7og.jpg",
          "duracao": null,
          "descricao": "A história de amor entre Asya e Volkan parece ser perfeita, mas com um pequeno detalhe. Por um fio de cabelo, tudo pode terminar em vingança."
        },
        {
          "id": "ep-11081324",
          "tipo": "episodio",
          "titulo": "Iludida - Sadakatsiz [DUB] S01E70",
          "numero": 70,
          "temporada": 1,
          "xtreamId": "11081324",
          "container": "mp4",
          "capa": "https://image.tmdb.org/t/p/w600_and_h900_bestv2/xC9vUFVIrxnhZiEYLeMDVqxj7og.jpg",
          "duracao": null,
          "descricao": "A história de amor entre Asya e Volkan parece ser perfeita, mas com um pequeno detalhe. Por um fio de cabelo, tudo pode terminar em vingança."
        },
        {
          "id": "ep-11081325",
          "tipo": "episodio",
          "titulo": "Iludida - Sadakatsiz [DUB] S01E71",
          "numero": 71,
          "temporada": 1,
          "xtreamId": "11081325",
          "container": "mp4",
          "capa": "https://image.tmdb.org/t/p/w600_and_h900_bestv2/xC9vUFVIrxnhZiEYLeMDVqxj7og.jpg",
          "duracao": null,
          "descricao": "A história de amor entre Asya e Volkan parece ser perfeita, mas com um pequeno detalhe. Por um fio de cabelo, tudo pode terminar em vingança."
        },
        {
          "id": "ep-11081326",
          "tipo": "episodio",
          "titulo": "Iludida - Sadakatsiz [DUB] S01E72",
          "numero": 72,
          "temporada": 1,
          "xtreamId": "11081326",
          "container": "mp4",
          "capa": "https://image.tmdb.org/t/p/w600_and_h900_bestv2/xC9vUFVIrxnhZiEYLeMDVqxj7og.jpg",
          "duracao": null,
          "descricao": "A história de amor entre Asya e Volkan parece ser perfeita, mas com um pequeno detalhe. Por um fio de cabelo, tudo pode terminar em vingança."
        },
        {
          "id": "ep-11081327",
          "tipo": "episodio",
          "titulo": "Iludida - Sadakatsiz [DUB] S01E73",
          "numero": 73,
          "temporada": 1,
          "xtreamId": "11081327",
          "container": "mp4",
          "capa": "https://image.tmdb.org/t/p/w600_and_h900_bestv2/xC9vUFVIrxnhZiEYLeMDVqxj7og.jpg",
          "duracao": null,
          "descricao": "A história de amor entre Asya e Volkan parece ser perfeita, mas com um pequeno detalhe. Por um fio de cabelo, tudo pode terminar em vingança."
        },
        {
          "id": "ep-11081328",
          "tipo": "episodio",
          "titulo": "Iludida - Sadakatsiz [DUB] S01E74",
          "numero": 74,
          "temporada": 1,
          "xtreamId": "11081328",
          "container": "mp4",
          "capa": "https://image.tmdb.org/t/p/w600_and_h900_bestv2/xC9vUFVIrxnhZiEYLeMDVqxj7og.jpg",
          "duracao": null,
          "descricao": "A história de amor entre Asya e Volkan parece ser perfeita, mas com um pequeno detalhe. Por um fio de cabelo, tudo pode terminar em vingança."
        },
        {
          "id": "ep-11081329",
          "tipo": "episodio",
          "titulo": "Iludida - Sadakatsiz [DUB] S01E75",
          "numero": 75,
          "temporada": 1,
          "xtreamId": "11081329",
          "container": "mp4",
          "capa": "https://image.tmdb.org/t/p/w600_and_h900_bestv2/xC9vUFVIrxnhZiEYLeMDVqxj7og.jpg",
          "duracao": null,
          "descricao": "A história de amor entre Asya e Volkan parece ser perfeita, mas com um pequeno detalhe. Por um fio de cabelo, tudo pode terminar em vingança."
        },
        {
          "id": "ep-11081330",
          "tipo": "episodio",
          "titulo": "Iludida - Sadakatsiz [DUB] S01E76",
          "numero": 76,
          "temporada": 1,
          "xtreamId": "11081330",
          "container": "mp4",
          "capa": "https://image.tmdb.org/t/p/w600_and_h900_bestv2/xC9vUFVIrxnhZiEYLeMDVqxj7og.jpg",
          "duracao": null,
          "descricao": "A história de amor entre Asya e Volkan parece ser perfeita, mas com um pequeno detalhe. Por um fio de cabelo, tudo pode terminar em vingança."
        },
        {
          "id": "ep-11081331",
          "tipo": "episodio",
          "titulo": "Iludida - Sadakatsiz [DUB] S01E77",
          "numero": 77,
          "temporada": 1,
          "xtreamId": "11081331",
          "container": "mp4",
          "capa": "https://image.tmdb.org/t/p/w600_and_h900_bestv2/xC9vUFVIrxnhZiEYLeMDVqxj7og.jpg",
          "duracao": null,
          "descricao": "A história de amor entre Asya e Volkan parece ser perfeita, mas com um pequeno detalhe. Por um fio de cabelo, tudo pode terminar em vingança."
        },
        {
          "id": "ep-11081332",
          "tipo": "episodio",
          "titulo": "Iludida - Sadakatsiz [DUB] S01E78",
          "numero": 78,
          "temporada": 1,
          "xtreamId": "11081332",
          "container": "mp4",
          "capa": "https://image.tmdb.org/t/p/w600_and_h900_bestv2/xC9vUFVIrxnhZiEYLeMDVqxj7og.jpg",
          "duracao": null,
          "descricao": "A história de amor entre Asya e Volkan parece ser perfeita, mas com um pequeno detalhe. Por um fio de cabelo, tudo pode terminar em vingança."
        }
      ]
    },
    {
      "numero": 2,
      "nome": "Temporada 2",
      "episodios": [
        {
          "id": "ep-11081333",
          "tipo": "episodio",
          "titulo": "Iludida - Sadakatsiz [DUB] S02E01",
          "numero": 1,
          "temporada": 2,
          "xtreamId": "11081333",
          "container": "mp4",
          "capa": "https://image.tmdb.org/t/p/w600_and_h900_bestv2/xC9vUFVIrxnhZiEYLeMDVqxj7og.jpg",
          "duracao": null,
          "descricao": "A história de amor entre Asya e Volkan parece ser perfeita, mas com um pequeno detalhe. Por um fio de cabelo, tudo pode terminar em vingança."
        },
        {
          "id": "ep-11081334",
          "tipo": "episodio",
          "titulo": "Iludida - Sadakatsiz [DUB] S02E02",
          "numero": 2,
          "temporada": 2,
          "xtreamId": "11081334",
          "container": "mp4",
          "capa": "https://image.tmdb.org/t/p/w600_and_h900_bestv2/xC9vUFVIrxnhZiEYLeMDVqxj7og.jpg",
          "duracao": null,
          "descricao": "A história de amor entre Asya e Volkan parece ser perfeita, mas com um pequeno detalhe. Por um fio de cabelo, tudo pode terminar em vingança."
        },
        {
          "id": "ep-11081335",
          "tipo": "episodio",
          "titulo": "Iludida - Sadakatsiz [DUB] S02E03",
          "numero": 3,
          "temporada": 2,
          "xtreamId": "11081335",
          "container": "mp4",
          "capa": "https://image.tmdb.org/t/p/w600_and_h900_bestv2/xC9vUFVIrxnhZiEYLeMDVqxj7og.jpg",
          "duracao": null,
          "descricao": "A história de amor entre Asya e Volkan parece ser perfeita, mas com um pequeno detalhe. Por um fio de cabelo, tudo pode terminar em vingança."
        },
        {
          "id": "ep-11081336",
          "tipo": "episodio",
          "titulo": "Iludida - Sadakatsiz [DUB] S02E04",
          "numero": 4,
          "temporada": 2,
          "xtreamId": "11081336",
          "container": "mp4",
          "capa": "https://image.tmdb.org/t/p/w600_and_h900_bestv2/xC9vUFVIrxnhZiEYLeMDVqxj7og.jpg",
          "duracao": null,
          "descricao": "A história de amor entre Asya e Volkan parece ser perfeita, mas com um pequeno detalhe. Por um fio de cabelo, tudo pode terminar em vingança."
        },
        {
          "id": "ep-11081337",
          "tipo": "episodio",
          "titulo": "Iludida - Sadakatsiz [DUB] S02E05",
          "numero": 5,
          "temporada": 2,
          "xtreamId": "11081337",
          "container": "mp4",
          "capa": "https://image.tmdb.org/t/p/w600_and_h900_bestv2/xC9vUFVIrxnhZiEYLeMDVqxj7og.jpg",
          "duracao": null,
          "descricao": "A história de amor entre Asya e Volkan parece ser perfeita, mas com um pequeno detalhe. Por um fio de cabelo, tudo pode terminar em vingança."
        },
        {
          "id": "ep-11081338",
          "tipo": "episodio",
          "titulo": "Iludida - Sadakatsiz [DUB] S02E06",
          "numero": 6,
          "temporada": 2,
          "xtreamId": "11081338",
          "container": "mp4",
          "capa": "https://image.tmdb.org/t/p/w600_and_h900_bestv2/xC9vUFVIrxnhZiEYLeMDVqxj7og.jpg",
          "duracao": null,
          "descricao": "A história de amor entre Asya e Volkan parece ser perfeita, mas com um pequeno detalhe. Por um fio de cabelo, tudo pode terminar em vingança."
        },
        {
          "id": "ep-11081339",
          "tipo": "episodio",
          "titulo": "Iludida - Sadakatsiz [DUB] S02E07",
          "numero": 7,
          "temporada": 2,
          "xtreamId": "11081339",
          "container": "mp4",
          "capa": "https://image.tmdb.org/t/p/w600_and_h900_bestv2/xC9vUFVIrxnhZiEYLeMDVqxj7og.jpg",
          "duracao": null,
          "descricao": "A história de amor entre Asya e Volkan parece ser perfeita, mas com um pequeno detalhe. Por um fio de cabelo, tudo pode terminar em vingança."
        },
        {
          "id": "ep-11081340",
          "tipo": "episodio",
          "titulo": "Iludida - Sadakatsiz [DUB] S02E08",
          "numero": 8,
          "temporada": 2,
          "xtreamId": "11081340",
          "container": "mp4",
          "capa": "https://image.tmdb.org/t/p/w600_and_h900_bestv2/xC9vUFVIrxnhZiEYLeMDVqxj7og.jpg",
          "duracao": null,
          "descricao": "A história de amor entre Asya e Volkan parece ser perfeita, mas com um pequeno detalhe. Por um fio de cabelo, tudo pode terminar em vingança."
        },
        {
          "id": "ep-11081341",
          "tipo": "episodio",
          "titulo": "Iludida - Sadakatsiz [DUB] S02E09",
          "numero": 9,
          "temporada": 2,
          "xtreamId": "11081341",
          "container": "mp4",
          "capa": "https://image.tmdb.org/t/p/w600_and_h900_bestv2/xC9vUFVIrxnhZiEYLeMDVqxj7og.jpg",
          "duracao": null,
          "descricao": "A história de amor entre Asya e Volkan parece ser perfeita, mas com um pequeno detalhe. Por um fio de cabelo, tudo pode terminar em vingança."
        },
        {
          "id": "ep-11081342",
          "tipo": "episodio",
          "titulo": "Iludida - Sadakatsiz [DUB] S02E10",
          "numero": 10,
          "temporada": 2,
          "xtreamId": "11081342",
          "container": "mp4",
          "capa": "https://image.tmdb.org/t/p/w600_and_h900_bestv2/xC9vUFVIrxnhZiEYLeMDVqxj7og.jpg",
          "duracao": null,
          "descricao": "A história de amor entre Asya e Volkan parece ser perfeita, mas com um pequeno detalhe. Por um fio de cabelo, tudo pode terminar em vingança."
        },
        {
          "id": "ep-11081343",
          "tipo": "episodio",
          "titulo": "Iludida - Sadakatsiz [DUB] S02E11",
          "numero": 11,
          "temporada": 2,
          "xtreamId": "11081343",
          "container": "mp4",
          "capa": "https://image.tmdb.org/t/p/w600_and_h900_bestv2/xC9vUFVIrxnhZiEYLeMDVqxj7og.jpg",
          "duracao": null,
          "descricao": "A história de amor entre Asya e Volkan parece ser perfeita, mas com um pequeno detalhe. Por um fio de cabelo, tudo pode terminar em vingança."
        },
        {
          "id": "ep-11081344",
          "tipo": "episodio",
          "titulo": "Iludida - Sadakatsiz [DUB] S02E12",
          "numero": 12,
          "temporada": 2,
          "xtreamId": "11081344",
          "container": "mp4",
          "capa": "https://image.tmdb.org/t/p/w600_and_h900_bestv2/xC9vUFVIrxnhZiEYLeMDVqxj7og.jpg",
          "duracao": null,
          "descricao": "A história de amor entre Asya e Volkan parece ser perfeita, mas com um pequeno detalhe. Por um fio de cabelo, tudo pode terminar em vingança."
        },
        {
          "id": "ep-11081345",
          "tipo": "episodio",
          "titulo": "Iludida - Sadakatsiz [DUB] S02E13",
          "numero": 13,
          "temporada": 2,
          "xtreamId": "11081345",
          "container": "mp4",
          "capa": "https://image.tmdb.org/t/p/w600_and_h900_bestv2/xC9vUFVIrxnhZiEYLeMDVqxj7og.jpg",
          "duracao": null,
          "descricao": "A história de amor entre Asya e Volkan parece ser perfeita, mas com um pequeno detalhe. Por um fio de cabelo, tudo pode terminar em vingança."
        },
        {
          "id": "ep-11081346",
          "tipo": "episodio",
          "titulo": "Iludida - Sadakatsiz [DUB] S02E14",
          "numero": 14,
          "temporada": 2,
          "xtreamId": "11081346",
          "container": "mp4",
          "capa": "https://image.tmdb.org/t/p/w600_and_h900_bestv2/xC9vUFVIrxnhZiEYLeMDVqxj7og.jpg",
          "duracao": null,
          "descricao": "A história de amor entre Asya e Volkan parece ser perfeita, mas com um pequeno detalhe. Por um fio de cabelo, tudo pode terminar em vingança."
        },
        {
          "id": "ep-11081347",
          "tipo": "episodio",
          "titulo": "Iludida - Sadakatsiz [DUB] S02E15",
          "numero": 15,
          "temporada": 2,
          "xtreamId": "11081347",
          "container": "mp4",
          "capa": "https://image.tmdb.org/t/p/w600_and_h900_bestv2/xC9vUFVIrxnhZiEYLeMDVqxj7og.jpg",
          "duracao": null,
          "descricao": "A história de amor entre Asya e Volkan parece ser perfeita, mas com um pequeno detalhe. Por um fio de cabelo, tudo pode terminar em vingança."
        },
        {
          "id": "ep-11081348",
          "tipo": "episodio",
          "titulo": "Iludida - Sadakatsiz [DUB] S02E16",
          "numero": 16,
          "temporada": 2,
          "xtreamId": "11081348",
          "container": "mp4",
          "capa": "https://image.tmdb.org/t/p/w600_and_h900_bestv2/xC9vUFVIrxnhZiEYLeMDVqxj7og.jpg",
          "duracao": null,
          "descricao": "A história de amor entre Asya e Volkan parece ser perfeita, mas com um pequeno detalhe. Por um fio de cabelo, tudo pode terminar em vingança."
        },
        {
          "id": "ep-11081349",
          "tipo": "episodio",
          "titulo": "Iludida - Sadakatsiz [DUB] S02E17",
          "numero": 17,
          "temporada": 2,
          "xtreamId": "11081349",
          "container": "mp4",
          "capa": "https://image.tmdb.org/t/p/w600_and_h900_bestv2/xC9vUFVIrxnhZiEYLeMDVqxj7og.jpg",
          "duracao": null,
          "descricao": "A história de amor entre Asya e Volkan parece ser perfeita, mas com um pequeno detalhe. Por um fio de cabelo, tudo pode terminar em vingança."
        },
        {
          "id": "ep-11081350",
          "tipo": "episodio",
          "titulo": "Iludida - Sadakatsiz [DUB] S02E18",
          "numero": 18,
          "temporada": 2,
          "xtreamId": "11081350",
          "container": "mp4",
          "capa": "https://image.tmdb.org/t/p/w600_and_h900_bestv2/xC9vUFVIrxnhZiEYLeMDVqxj7og.jpg",
          "duracao": null,
          "descricao": "A história de amor entre Asya e Volkan parece ser perfeita, mas com um pequeno detalhe. Por um fio de cabelo, tudo pode terminar em vingança."
        },
        {
          "id": "ep-11081351",
          "tipo": "episodio",
          "titulo": "Iludida - Sadakatsiz [DUB] S02E19",
          "numero": 19,
          "temporada": 2,
          "xtreamId": "11081351",
          "container": "mp4",
          "capa": "https://image.tmdb.org/t/p/w600_and_h900_bestv2/xC9vUFVIrxnhZiEYLeMDVqxj7og.jpg",
          "duracao": null,
          "descricao": "A história de amor entre Asya e Volkan parece ser perfeita, mas com um pequeno detalhe. Por um fio de cabelo, tudo pode terminar em vingança."
        },
        {
          "id": "ep-11081352",
          "tipo": "episodio",
          "titulo": "Iludida - Sadakatsiz [DUB] S02E20",
          "numero": 20,
          "temporada": 2,
          "xtreamId": "11081352",
          "container": "mp4",
          "capa": "https://image.tmdb.org/t/p/w600_and_h900_bestv2/xC9vUFVIrxnhZiEYLeMDVqxj7og.jpg",
          "duracao": null,
          "descricao": "A história de amor entre Asya e Volkan parece ser perfeita, mas com um pequeno detalhe. Por um fio de cabelo, tudo pode terminar em vingança."
        },
        {
          "id": "ep-11081353",
          "tipo": "episodio",
          "titulo": "Iludida - Sadakatsiz [DUB] S02E21",
          "numero": 21,
          "temporada": 2,
          "xtreamId": "11081353",
          "container": "mp4",
          "capa": "https://image.tmdb.org/t/p/w600_and_h900_bestv2/xC9vUFVIrxnhZiEYLeMDVqxj7og.jpg",
          "duracao": null,
          "descricao": "A história de amor entre Asya e Volkan parece ser perfeita, mas com um pequeno detalhe. Por um fio de cabelo, tudo pode terminar em vingança."
        },
        {
          "id": "ep-11081354",
          "tipo": "episodio",
          "titulo": "Iludida - Sadakatsiz [DUB] S02E22",
          "numero": 22,
          "temporada": 2,
          "xtreamId": "11081354",
          "container": "mp4",
          "capa": "https://image.tmdb.org/t/p/w600_and_h900_bestv2/xC9vUFVIrxnhZiEYLeMDVqxj7og.jpg",
          "duracao": null,
          "descricao": "A história de amor entre Asya e Volkan parece ser perfeita, mas com um pequeno detalhe. Por um fio de cabelo, tudo pode terminar em vingança."
        },
        {
          "id": "ep-11081355",
          "tipo": "episodio",
          "titulo": "Iludida - Sadakatsiz [DUB] S02E23",
          "numero": 23,
          "temporada": 2,
          "xtreamId": "11081355",
          "container": "mp4",
          "capa": "https://image.tmdb.org/t/p/w600_and_h900_bestv2/xC9vUFVIrxnhZiEYLeMDVqxj7og.jpg",
          "duracao": null,
          "descricao": "A história de amor entre Asya e Volkan parece ser perfeita, mas com um pequeno detalhe. Por um fio de cabelo, tudo pode terminar em vingança."
        },
        {
          "id": "ep-11081356",
          "tipo": "episodio",
          "titulo": "Iludida - Sadakatsiz [DUB] S02E24",
          "numero": 24,
          "temporada": 2,
          "xtreamId": "11081356",
          "container": "mp4",
          "capa": "https://image.tmdb.org/t/p/w600_and_h900_bestv2/xC9vUFVIrxnhZiEYLeMDVqxj7og.jpg",
          "duracao": null,
          "descricao": "A história de amor entre Asya e Volkan parece ser perfeita, mas com um pequeno detalhe. Por um fio de cabelo, tudo pode terminar em vingança."
        },
        {
          "id": "ep-11081357",
          "tipo": "episodio",
          "titulo": "Iludida - Sadakatsiz [DUB] S02E25",
          "numero": 25,
          "temporada": 2,
          "xtreamId": "11081357",
          "container": "mp4",
          "capa": "https://image.tmdb.org/t/p/w600_and_h900_bestv2/xC9vUFVIrxnhZiEYLeMDVqxj7og.jpg",
          "duracao": null,
          "descricao": "A história de amor entre Asya e Volkan parece ser perfeita, mas com um pequeno detalhe. Por um fio de cabelo, tudo pode terminar em vingança."
        },
        {
          "id": "ep-11081358",
          "tipo": "episodio",
          "titulo": "Iludida - Sadakatsiz [DUB] S02E26",
          "numero": 26,
          "temporada": 2,
          "xtreamId": "11081358",
          "container": "mp4",
          "capa": "https://image.tmdb.org/t/p/w600_and_h900_bestv2/xC9vUFVIrxnhZiEYLeMDVqxj7og.jpg",
          "duracao": null,
          "descricao": "A história de amor entre Asya e Volkan parece ser perfeita, mas com um pequeno detalhe. Por um fio de cabelo, tudo pode terminar em vingança."
        },
        {
          "id": "ep-11081359",
          "tipo": "episodio",
          "titulo": "Iludida - Sadakatsiz [DUB] S02E27",
          "numero": 27,
          "temporada": 2,
          "xtreamId": "11081359",
          "container": "mp4",
          "capa": "https://image.tmdb.org/t/p/w600_and_h900_bestv2/xC9vUFVIrxnhZiEYLeMDVqxj7og.jpg",
          "duracao": null,
          "descricao": "A história de amor entre Asya e Volkan parece ser perfeita, mas com um pequeno detalhe. Por um fio de cabelo, tudo pode terminar em vingança."
        },
        {
          "id": "ep-11081360",
          "tipo": "episodio",
          "titulo": "Iludida - Sadakatsiz [DUB] S02E28",
          "numero": 28,
          "temporada": 2,
          "xtreamId": "11081360",
          "container": "mp4",
          "capa": "https://image.tmdb.org/t/p/w600_and_h900_bestv2/xC9vUFVIrxnhZiEYLeMDVqxj7og.jpg",
          "duracao": null,
          "descricao": "A história de amor entre Asya e Volkan parece ser perfeita, mas com um pequeno detalhe. Por um fio de cabelo, tudo pode terminar em vingança."
        },
        {
          "id": "ep-11081361",
          "tipo": "episodio",
          "titulo": "Iludida - Sadakatsiz [DUB] S02E29",
          "numero": 29,
          "temporada": 2,
          "xtreamId": "11081361",
          "container": "mp4",
          "capa": "https://image.tmdb.org/t/p/w600_and_h900_bestv2/xC9vUFVIrxnhZiEYLeMDVqxj7og.jpg",
          "duracao": null,
          "descricao": "A história de amor entre Asya e Volkan parece ser perfeita, mas com um pequeno detalhe. Por um fio de cabelo, tudo pode terminar em vingança."
        },
        {
          "id": "ep-11081362",
          "tipo": "episodio",
          "titulo": "Iludida - Sadakatsiz [DUB] S02E30",
          "numero": 30,
          "temporada": 2,
          "xtreamId": "11081362",
          "container": "mp4",
          "capa": "https://image.tmdb.org/t/p/w600_and_h900_bestv2/xC9vUFVIrxnhZiEYLeMDVqxj7og.jpg",
          "duracao": null,
          "descricao": "A história de amor entre Asya e Volkan parece ser perfeita, mas com um pequeno detalhe. Por um fio de cabelo, tudo pode terminar em vingança."
        },
        {
          "id": "ep-11081363",
          "tipo": "episodio",
          "titulo": "Iludida - Sadakatsiz [DUB] S02E31",
          "numero": 31,
          "temporada": 2,
          "xtreamId": "11081363",
          "container": "mp4",
          "capa": "https://image.tmdb.org/t/p/w600_and_h900_bestv2/xC9vUFVIrxnhZiEYLeMDVqxj7og.jpg",
          "duracao": null,
          "descricao": "A história de amor entre Asya e Volkan parece ser perfeita, mas com um pequeno detalhe. Por um fio de cabelo, tudo pode terminar em vingança."
        },
        {
          "id": "ep-11081364",
          "tipo": "episodio",
          "titulo": "Iludida - Sadakatsiz [DUB] S02E32",
          "numero": 32,
          "temporada": 2,
          "xtreamId": "11081364",
          "container": "mp4",
          "capa": "https://image.tmdb.org/t/p/w600_and_h900_bestv2/xC9vUFVIrxnhZiEYLeMDVqxj7og.jpg",
          "duracao": null,
          "descricao": "A história de amor entre Asya e Volkan parece ser perfeita, mas com um pequeno detalhe. Por um fio de cabelo, tudo pode terminar em vingança."
        },
        {
          "id": "ep-11081365",
          "tipo": "episodio",
          "titulo": "Iludida - Sadakatsiz [DUB] S02E33",
          "numero": 33,
          "temporada": 2,
          "xtreamId": "11081365",
          "container": "mp4",
          "capa": "https://image.tmdb.org/t/p/w600_and_h900_bestv2/xC9vUFVIrxnhZiEYLeMDVqxj7og.jpg",
          "duracao": null,
          "descricao": "A história de amor entre Asya e Volkan parece ser perfeita, mas com um pequeno detalhe. Por um fio de cabelo, tudo pode terminar em vingança."
        },
        {
          "id": "ep-11081366",
          "tipo": "episodio",
          "titulo": "Iludida - Sadakatsiz [DUB] S02E34",
          "numero": 34,
          "temporada": 2,
          "xtreamId": "11081366",
          "container": "mp4",
          "capa": "https://image.tmdb.org/t/p/w600_and_h900_bestv2/xC9vUFVIrxnhZiEYLeMDVqxj7og.jpg",
          "duracao": null,
          "descricao": "A história de amor entre Asya e Volkan parece ser perfeita, mas com um pequeno detalhe. Por um fio de cabelo, tudo pode terminar em vingança."
        },
        {
          "id": "ep-11081367",
          "tipo": "episodio",
          "titulo": "Iludida - Sadakatsiz [DUB] S02E35",
          "numero": 35,
          "temporada": 2,
          "xtreamId": "11081367",
          "container": "mp4",
          "capa": "https://image.tmdb.org/t/p/w600_and_h900_bestv2/xC9vUFVIrxnhZiEYLeMDVqxj7og.jpg",
          "duracao": null,
          "descricao": "A história de amor entre Asya e Volkan parece ser perfeita, mas com um pequeno detalhe. Por um fio de cabelo, tudo pode terminar em vingança."
        },
        {
          "id": "ep-11081368",
          "tipo": "episodio",
          "titulo": "Iludida - Sadakatsiz [DUB] S02E36",
          "numero": 36,
          "temporada": 2,
          "xtreamId": "11081368",
          "container": "mp4",
          "capa": "https://image.tmdb.org/t/p/w600_and_h900_bestv2/xC9vUFVIrxnhZiEYLeMDVqxj7og.jpg",
          "duracao": null,
          "descricao": "A história de amor entre Asya e Volkan parece ser perfeita, mas com um pequeno detalhe. Por um fio de cabelo, tudo pode terminar em vingança."
        },
        {
          "id": "ep-11081369",
          "tipo": "episodio",
          "titulo": "Iludida - Sadakatsiz [DUB] S02E37",
          "numero": 37,
          "temporada": 2,
          "xtreamId": "11081369",
          "container": "mp4",
          "capa": "https://image.tmdb.org/t/p/w600_and_h900_bestv2/xC9vUFVIrxnhZiEYLeMDVqxj7og.jpg",
          "duracao": null,
          "descricao": "A história de amor entre Asya e Volkan parece ser perfeita, mas com um pequeno detalhe. Por um fio de cabelo, tudo pode terminar em vingança."
        },
        {
          "id": "ep-11081370",
          "tipo": "episodio",
          "titulo": "Iludida - Sadakatsiz [DUB] S02E38",
          "numero": 38,
          "temporada": 2,
          "xtreamId": "11081370",
          "container": "mp4",
          "capa": "https://image.tmdb.org/t/p/w600_and_h900_bestv2/xC9vUFVIrxnhZiEYLeMDVqxj7og.jpg",
          "duracao": null,
          "descricao": "A história de amor entre Asya e Volkan parece ser perfeita, mas com um pequeno detalhe. Por um fio de cabelo, tudo pode terminar em vingança."
        },
        {
          "id": "ep-11081371",
          "tipo": "episodio",
          "titulo": "Iludida - Sadakatsiz [DUB] S02E39",
          "numero": 39,
          "temporada": 2,
          "xtreamId": "11081371",
          "container": "mp4",
          "capa": "https://image.tmdb.org/t/p/w600_and_h900_bestv2/xC9vUFVIrxnhZiEYLeMDVqxj7og.jpg",
          "duracao": null,
          "descricao": "A história de amor entre Asya e Volkan parece ser perfeita, mas com um pequeno detalhe. Por um fio de cabelo, tudo pode terminar em vingança."
        },
        {
          "id": "ep-11081372",
          "tipo": "episodio",
          "titulo": "Iludida - Sadakatsiz [DUB] S02E40",
          "numero": 40,
          "temporada": 2,
          "xtreamId": "11081372",
          "container": "mp4",
          "capa": "https://image.tmdb.org/t/p/w600_and_h900_bestv2/xC9vUFVIrxnhZiEYLeMDVqxj7og.jpg",
          "duracao": null,
          "descricao": "A história de amor entre Asya e Volkan parece ser perfeita, mas com um pequeno detalhe. Por um fio de cabelo, tudo pode terminar em vingança."
        },
        {
          "id": "ep-11081373",
          "tipo": "episodio",
          "titulo": "Iludida - Sadakatsiz [DUB] S02E41",
          "numero": 41,
          "temporada": 2,
          "xtreamId": "11081373",
          "container": "mp4",
          "capa": "https://image.tmdb.org/t/p/w600_and_h900_bestv2/xC9vUFVIrxnhZiEYLeMDVqxj7og.jpg",
          "duracao": null,
          "descricao": "A história de amor entre Asya e Volkan parece ser perfeita, mas com um pequeno detalhe. Por um fio de cabelo, tudo pode terminar em vingança."
        },
        {
          "id": "ep-11081374",
          "tipo": "episodio",
          "titulo": "Iludida - Sadakatsiz [DUB] S02E42",
          "numero": 42,
          "temporada": 2,
          "xtreamId": "11081374",
          "container": "mp4",
          "capa": "https://image.tmdb.org/t/p/w600_and_h900_bestv2/xC9vUFVIrxnhZiEYLeMDVqxj7og.jpg",
          "duracao": null,
          "descricao": "A história de amor entre Asya e Volkan parece ser perfeita, mas com um pequeno detalhe. Por um fio de cabelo, tudo pode terminar em vingança."
        },
        {
          "id": "ep-11081375",
          "tipo": "episodio",
          "titulo": "Iludida - Sadakatsiz [DUB] S02E43",
          "numero": 43,
          "temporada": 2,
          "xtreamId": "11081375",
          "container": "mp4",
          "capa": "https://image.tmdb.org/t/p/w600_and_h900_bestv2/xC9vUFVIrxnhZiEYLeMDVqxj7og.jpg",
          "duracao": null,
          "descricao": "A história de amor entre Asya e Volkan parece ser perfeita, mas com um pequeno detalhe. Por um fio de cabelo, tudo pode terminar em vingança."
        },
        {
          "id": "ep-11081376",
          "tipo": "episodio",
          "titulo": "Iludida - Sadakatsiz [DUB] S02E44",
          "numero": 44,
          "temporada": 2,
          "xtreamId": "11081376",
          "container": "mp4",
          "capa": "https://image.tmdb.org/t/p/w600_and_h900_bestv2/xC9vUFVIrxnhZiEYLeMDVqxj7og.jpg",
          "duracao": null,
          "descricao": "A história de amor entre Asya e Volkan parece ser perfeita, mas com um pequeno detalhe. Por um fio de cabelo, tudo pode terminar em vingança."
        },
        {
          "id": "ep-11081377",
          "tipo": "episodio",
          "titulo": "Iludida - Sadakatsiz [DUB] S02E45",
          "numero": 45,
          "temporada": 2,
          "xtreamId": "11081377",
          "container": "mp4",
          "capa": "https://image.tmdb.org/t/p/w600_and_h900_bestv2/xC9vUFVIrxnhZiEYLeMDVqxj7og.jpg",
          "duracao": null,
          "descricao": "A história de amor entre Asya e Volkan parece ser perfeita, mas com um pequeno detalhe. Por um fio de cabelo, tudo pode terminar em vingança."
        },
        {
          "id": "ep-11081378",
          "tipo": "episodio",
          "titulo": "Iludida - Sadakatsiz [DUB] S02E46",
          "numero": 46,
          "temporada": 2,
          "xtreamId": "11081378",
          "container": "mp4",
          "capa": "https://image.tmdb.org/t/p/w600_and_h900_bestv2/xC9vUFVIrxnhZiEYLeMDVqxj7og.jpg",
          "duracao": null,
          "descricao": "A história de amor entre Asya e Volkan parece ser perfeita, mas com um pequeno detalhe. Por um fio de cabelo, tudo pode terminar em vingança."
        },
        {
          "id": "ep-11081379",
          "tipo": "episodio",
          "titulo": "Iludida - Sadakatsiz [DUB] S02E47",
          "numero": 47,
          "temporada": 2,
          "xtreamId": "11081379",
          "container": "mp4",
          "capa": "https://image.tmdb.org/t/p/w600_and_h900_bestv2/xC9vUFVIrxnhZiEYLeMDVqxj7og.jpg",
          "duracao": null,
          "descricao": "A história de amor entre Asya e Volkan parece ser perfeita, mas com um pequeno detalhe. Por um fio de cabelo, tudo pode terminar em vingança."
        },
        {
          "id": "ep-11081380",
          "tipo": "episodio",
          "titulo": "Iludida - Sadakatsiz [DUB] S02E48",
          "numero": 48,
          "temporada": 2,
          "xtreamId": "11081380",
          "container": "mp4",
          "capa": "https://image.tmdb.org/t/p/w600_and_h900_bestv2/xC9vUFVIrxnhZiEYLeMDVqxj7og.jpg",
          "duracao": null,
          "descricao": "A história de amor entre Asya e Volkan parece ser perfeita, mas com um pequeno detalhe. Por um fio de cabelo, tudo pode terminar em vingança."
        },
        {
          "id": "ep-11081381",
          "tipo": "episodio",
          "titulo": "Iludida - Sadakatsiz [DUB] S02E49",
          "numero": 49,
          "temporada": 2,
          "xtreamId": "11081381",
          "container": "mp4",
          "capa": "https://image.tmdb.org/t/p/w600_and_h900_bestv2/xC9vUFVIrxnhZiEYLeMDVqxj7og.jpg",
          "duracao": null,
          "descricao": "A história de amor entre Asya e Volkan parece ser perfeita, mas com um pequeno detalhe. Por um fio de cabelo, tudo pode terminar em vingança."
        },
        {
          "id": "ep-11081382",
          "tipo": "episodio",
          "titulo": "Iludida - Sadakatsiz [DUB] S02E50",
          "numero": 50,
          "temporada": 2,
          "xtreamId": "11081382",
          "container": "mp4",
          "capa": "https://image.tmdb.org/t/p/w600_and_h900_bestv2/xC9vUFVIrxnhZiEYLeMDVqxj7og.jpg",
          "duracao": null,
          "descricao": "A história de amor entre Asya e Volkan parece ser perfeita, mas com um pequeno detalhe. Por um fio de cabelo, tudo pode terminar em vingança."
        },
        {
          "id": "ep-11081383",
          "tipo": "episodio",
          "titulo": "Iludida - Sadakatsiz [DUB] S02E51",
          "numero": 51,
          "temporada": 2,
          "xtreamId": "11081383",
          "container": "mp4",
          "capa": "https://image.tmdb.org/t/p/w600_and_h900_bestv2/xC9vUFVIrxnhZiEYLeMDVqxj7og.jpg",
          "duracao": null,
          "descricao": "A história de amor entre Asya e Volkan parece ser perfeita, mas com um pequeno detalhe. Por um fio de cabelo, tudo pode terminar em vingança."
        },
        {
          "id": "ep-11081384",
          "tipo": "episodio",
          "titulo": "Iludida - Sadakatsiz [DUB] S02E52",
          "numero": 52,
          "temporada": 2,
          "xtreamId": "11081384",
          "container": "mp4",
          "capa": "https://image.tmdb.org/t/p/w600_and_h900_bestv2/xC9vUFVIrxnhZiEYLeMDVqxj7og.jpg",
          "duracao": null,
          "descricao": "A história de amor entre Asya e Volkan parece ser perfeita, mas com um pequeno detalhe. Por um fio de cabelo, tudo pode terminar em vingança."
        },
        {
          "id": "ep-11081385",
          "tipo": "episodio",
          "titulo": "Iludida - Sadakatsiz [DUB] S02E53",
          "numero": 53,
          "temporada": 2,
          "xtreamId": "11081385",
          "container": "mp4",
          "capa": "https://image.tmdb.org/t/p/w600_and_h900_bestv2/xC9vUFVIrxnhZiEYLeMDVqxj7og.jpg",
          "duracao": null,
          "descricao": "A história de amor entre Asya e Volkan parece ser perfeita, mas com um pequeno detalhe. Por um fio de cabelo, tudo pode terminar em vingança."
        },
        {
          "id": "ep-11081386",
          "tipo": "episodio",
          "titulo": "Iludida - Sadakatsiz [DUB] S02E54",
          "numero": 54,
          "temporada": 2,
          "xtreamId": "11081386",
          "container": "mp4",
          "capa": "https://image.tmdb.org/t/p/w600_and_h900_bestv2/xC9vUFVIrxnhZiEYLeMDVqxj7og.jpg",
          "duracao": null,
          "descricao": "A história de amor entre Asya e Volkan parece ser perfeita, mas com um pequeno detalhe. Por um fio de cabelo, tudo pode terminar em vingança."
        },
        {
          "id": "ep-11081387",
          "tipo": "episodio",
          "titulo": "Iludida - Sadakatsiz [DUB] S02E55",
          "numero": 55,
          "temporada": 2,
          "xtreamId": "11081387",
          "container": "mp4",
          "capa": "https://image.tmdb.org/t/p/w600_and_h900_bestv2/xC9vUFVIrxnhZiEYLeMDVqxj7og.jpg",
          "duracao": null,
          "descricao": "A história de amor entre Asya e Volkan parece ser perfeita, mas com um pequeno detalhe. Por um fio de cabelo, tudo pode terminar em vingança."
        },
        {
          "id": "ep-11081388",
          "tipo": "episodio",
          "titulo": "Iludida - Sadakatsiz [DUB] S02E56",
          "numero": 56,
          "temporada": 2,
          "xtreamId": "11081388",
          "container": "mp4",
          "capa": "https://image.tmdb.org/t/p/w600_and_h900_bestv2/xC9vUFVIrxnhZiEYLeMDVqxj7og.jpg",
          "duracao": null,
          "descricao": "A história de amor entre Asya e Volkan parece ser perfeita, mas com um pequeno detalhe. Por um fio de cabelo, tudo pode terminar em vingança."
        },
        {
          "id": "ep-11081389",
          "tipo": "episodio",
          "titulo": "Iludida - Sadakatsiz [DUB] S02E57",
          "numero": 57,
          "temporada": 2,
          "xtreamId": "11081389",
          "container": "mp4",
          "capa": "https://image.tmdb.org/t/p/w600_and_h900_bestv2/xC9vUFVIrxnhZiEYLeMDVqxj7og.jpg",
          "duracao": null,
          "descricao": "A história de amor entre Asya e Volkan parece ser perfeita, mas com um pequeno detalhe. Por um fio de cabelo, tudo pode terminar em vingança."
        },
        {
          "id": "ep-11081390",
          "tipo": "episodio",
          "titulo": "Iludida - Sadakatsiz [DUB] S02E58",
          "numero": 58,
          "temporada": 2,
          "xtreamId": "11081390",
          "container": "mp4",
          "capa": "https://image.tmdb.org/t/p/w600_and_h900_bestv2/xC9vUFVIrxnhZiEYLeMDVqxj7og.jpg",
          "duracao": null,
          "descricao": "A história de amor entre Asya e Volkan parece ser perfeita, mas com um pequeno detalhe. Por um fio de cabelo, tudo pode terminar em vingança."
        },
        {
          "id": "ep-11081391",
          "tipo": "episodio",
          "titulo": "Iludida - Sadakatsiz [DUB] S02E59",
          "numero": 59,
          "temporada": 2,
          "xtreamId": "11081391",
          "container": "mp4",
          "capa": "https://image.tmdb.org/t/p/w600_and_h900_bestv2/xC9vUFVIrxnhZiEYLeMDVqxj7og.jpg",
          "duracao": null,
          "descricao": "A história de amor entre Asya e Volkan parece ser perfeita, mas com um pequeno detalhe. Por um fio de cabelo, tudo pode terminar em vingança."
        },
        {
          "id": "ep-11081392",
          "tipo": "episodio",
          "titulo": "Iludida - Sadakatsiz [DUB] S02E60",
          "numero": 60,
          "temporada": 2,
          "xtreamId": "11081392",
          "container": "mp4",
          "capa": "https://image.tmdb.org/t/p/w600_and_h900_bestv2/xC9vUFVIrxnhZiEYLeMDVqxj7og.jpg",
          "duracao": null,
          "descricao": "A história de amor entre Asya e Volkan parece ser perfeita, mas com um pequeno detalhe. Por um fio de cabelo, tudo pode terminar em vingança."
        },
        {
          "id": "ep-11081393",
          "tipo": "episodio",
          "titulo": "Iludida - Sadakatsiz [DUB] S02E61",
          "numero": 61,
          "temporada": 2,
          "xtreamId": "11081393",
          "container": "mp4",
          "capa": "https://image.tmdb.org/t/p/w600_and_h900_bestv2/xC9vUFVIrxnhZiEYLeMDVqxj7og.jpg",
          "duracao": null,
          "descricao": "A história de amor entre Asya e Volkan parece ser perfeita, mas com um pequeno detalhe. Por um fio de cabelo, tudo pode terminar em vingança."
        },
        {
          "id": "ep-11081394",
          "tipo": "episodio",
          "titulo": "Iludida - Sadakatsiz [DUB] S02E62",
          "numero": 62,
          "temporada": 2,
          "xtreamId": "11081394",
          "container": "mp4",
          "capa": "https://image.tmdb.org/t/p/w600_and_h900_bestv2/xC9vUFVIrxnhZiEYLeMDVqxj7og.jpg",
          "duracao": null,
          "descricao": "A história de amor entre Asya e Volkan parece ser perfeita, mas com um pequeno detalhe. Por um fio de cabelo, tudo pode terminar em vingança."
        },
        {
          "id": "ep-11081395",
          "tipo": "episodio",
          "titulo": "Iludida - Sadakatsiz [DUB] S02E63",
          "numero": 63,
          "temporada": 2,
          "xtreamId": "11081395",
          "container": "mp4",
          "capa": "https://image.tmdb.org/t/p/w600_and_h900_bestv2/xC9vUFVIrxnhZiEYLeMDVqxj7og.jpg",
          "duracao": null,
          "descricao": "A história de amor entre Asya e Volkan parece ser perfeita, mas com um pequeno detalhe. Por um fio de cabelo, tudo pode terminar em vingança."
        },
        {
          "id": "ep-11081396",
          "tipo": "episodio",
          "titulo": "Iludida - Sadakatsiz [DUB] S02E64",
          "numero": 64,
          "temporada": 2,
          "xtreamId": "11081396",
          "container": "mp4",
          "capa": "https://image.tmdb.org/t/p/w600_and_h900_bestv2/xC9vUFVIrxnhZiEYLeMDVqxj7og.jpg",
          "duracao": null,
          "descricao": "A história de amor entre Asya e Volkan parece ser perfeita, mas com um pequeno detalhe. Por um fio de cabelo, tudo pode terminar em vingança."
        },
        {
          "id": "ep-11081397",
          "tipo": "episodio",
          "titulo": "Iludida - Sadakatsiz [DUB] S02E65",
          "numero": 65,
          "temporada": 2,
          "xtreamId": "11081397",
          "container": "mp4",
          "capa": "https://image.tmdb.org/t/p/w600_and_h900_bestv2/xC9vUFVIrxnhZiEYLeMDVqxj7og.jpg",
          "duracao": null,
          "descricao": "A história de amor entre Asya e Volkan parece ser perfeita, mas com um pequeno detalhe. Por um fio de cabelo, tudo pode terminar em vingança."
        },
        {
          "id": "ep-11081398",
          "tipo": "episodio",
          "titulo": "Iludida - Sadakatsiz [DUB] S02E66",
          "numero": 66,
          "temporada": 2,
          "xtreamId": "11081398",
          "container": "mp4",
          "capa": "https://image.tmdb.org/t/p/w600_and_h900_bestv2/xC9vUFVIrxnhZiEYLeMDVqxj7og.jpg",
          "duracao": null,
          "descricao": "A história de amor entre Asya e Volkan parece ser perfeita, mas com um pequeno detalhe. Por um fio de cabelo, tudo pode terminar em vingança."
        },
        {
          "id": "ep-11081399",
          "tipo": "episodio",
          "titulo": "Iludida - Sadakatsiz [DUB] S02E67",
          "numero": 67,
          "temporada": 2,
          "xtreamId": "11081399",
          "container": "mp4",
          "capa": "https://image.tmdb.org/t/p/w600_and_h900_bestv2/xC9vUFVIrxnhZiEYLeMDVqxj7og.jpg",
          "duracao": null,
          "descricao": "A história de amor entre Asya e Volkan parece ser perfeita, mas com um pequeno detalhe. Por um fio de cabelo, tudo pode terminar em vingança."
        },
        {
          "id": "ep-11081400",
          "tipo": "episodio",
          "titulo": "Iludida - Sadakatsiz [DUB] S02E68",
          "numero": 68,
          "temporada": 2,
          "xtreamId": "11081400",
          "container": "mp4",
          "capa": "https://image.tmdb.org/t/p/w600_and_h900_bestv2/xC9vUFVIrxnhZiEYLeMDVqxj7og.jpg",
          "duracao": null,
          "descricao": "A história de amor entre Asya e Volkan parece ser perfeita, mas com um pequeno detalhe. Por um fio de cabelo, tudo pode terminar em vingança."
        },
        {
          "id": "ep-11081401",
          "tipo": "episodio",
          "titulo": "Iludida - Sadakatsiz [DUB] S02E69",
          "numero": 69,
          "temporada": 2,
          "xtreamId": "11081401",
          "container": "mp4",
          "capa": "https://image.tmdb.org/t/p/w600_and_h900_bestv2/xC9vUFVIrxnhZiEYLeMDVqxj7og.jpg",
          "duracao": null,
          "descricao": "A história de amor entre Asya e Volkan parece ser perfeita, mas com um pequeno detalhe. Por um fio de cabelo, tudo pode terminar em vingança."
        },
        {
          "id": "ep-11081402",
          "tipo": "episodio",
          "titulo": "Iludida - Sadakatsiz [DUB] S02E70",
          "numero": 70,
          "temporada": 2,
          "xtreamId": "11081402",
          "container": "mp4",
          "capa": "https://image.tmdb.org/t/p/w600_and_h900_bestv2/xC9vUFVIrxnhZiEYLeMDVqxj7og.jpg",
          "duracao": null,
          "descricao": "A história de amor entre Asya e Volkan parece ser perfeita, mas com um pequeno detalhe. Por um fio de cabelo, tudo pode terminar em vingança."
        },
        {
          "id": "ep-11081403",
          "tipo": "episodio",
          "titulo": "Iludida - Sadakatsiz [DUB] S02E71",
          "numero": 71,
          "temporada": 2,
          "xtreamId": "11081403",
          "container": "mp4",
          "capa": "https://image.tmdb.org/t/p/w600_and_h900_bestv2/xC9vUFVIrxnhZiEYLeMDVqxj7og.jpg",
          "duracao": null,
          "descricao": "A história de amor entre Asya e Volkan parece ser perfeita, mas com um pequeno detalhe. Por um fio de cabelo, tudo pode terminar em vingança."
        }
      ]
    }
  ],
  "totalTemporadas": 2,
  "totalEpisodios": 149,
  "tituloOriginal": "Sadakatsiz",
  "dataLancamento": "2020-10-07"
}