{
  "id": "palpitacoes-carpinti",
  "tipo": "serie",
  "titulo": "Palpitacoes - Carpinti",
  "ano": null,
  "descricao": "Uma pequena cidade nota estranhas mortes no deserto. Há minhocas gigantes sob a areia. Eles podem ouvir a localização das pessoas através da vibração de seu movimento. Finalmente, eles os explodem com dinamite.",
  "generos": [
    "TURCAS | MEXICANAS"
  ],
  "capa": "https://image.tmdb.org/t/p/w600_and_h900_bestv2/uJXjZ3OgU8v0HKUPbHk1DZUW3m9.jpg",
  "banner": "https://image.tmdb.org/t/p/original/dWb0frW3VzOLlRRijrAQLJpAzde.jpg",
  "tmdbId": null,
  "nota": 6,
  "xtreamSeriesId": 8078,
  "temporadas": [
    {
      "numero": 1,
      "nome": "Temporada 1",
      "episodios": [
        {
          "id": "ep-11092604",
          "tipo": "episodio",
          "titulo": "Palpitacoes - Carpinti [L] S01E01",
          "numero": 1,
          "temporada": 1,
          "xtreamId": "11092604",
          "container": "mp4",
          "capa": "https://image.tmdb.org/t/p/w600_and_h900_bestv2/uJXjZ3OgU8v0HKUPbHk1DZUW3m9.jpg",
          "duracao": null,
          "descricao": "Uma pequena cidade nota estranhas mortes no deserto. Há minhocas gigantes sob a areia. Eles podem ouvir a localização das pessoas através da vibração de seu movimento. Finalmente, eles os explodem com dinamite."
        },
        {
          "id": "ep-11092605",
          "tipo": "episodio",
          "titulo": "Palpitacoes - Carpinti [L] S01E02",
          "numero": 2,
          "temporada": 1,
          "xtreamId": "11092605",
          "container": "mp4",
          "capa": "https://image.tmdb.org/t/p/w600_and_h900_bestv2/uJXjZ3OgU8v0HKUPbHk1DZUW3m9.jpg",
          "duracao": null,
          "descricao": "Uma pequena cidade nota estranhas mortes no deserto. Há minhocas gigantes sob a areia. Eles podem ouvir a localização das pessoas através da vibração de seu movimento. Finalmente, eles os explodem com dinamite."
        },
        {
          "id": "ep-11092606",
          "tipo": "episodio",
          "titulo": "Palpitacoes - Carpinti [L] S01E03",
          "numero": 3,
          "temporada": 1,
          "xtreamId": "11092606",
          "container": "mp4",
          "capa": "https://image.tmdb.org/t/p/w600_and_h900_bestv2/uJXjZ3OgU8v0HKUPbHk1DZUW3m9.jpg",
          "duracao": null,
          "descricao": "Uma pequena cidade nota estranhas mortes no deserto. Há minhocas gigantes sob a areia. Eles podem ouvir a localização das pessoas através da vibração de seu movimento. Finalmente, eles os explodem com dinamite."
        },
        {
          "id": "ep-11092607",
          "tipo": "episodio",
          "titulo": "Palpitacoes - Carpinti [L] S01E04",
          "numero": 4,
          "temporada": 1,
          "xtreamId": "11092607",
          "container": "mp4",
          "capa": "https://image.tmdb.org/t/p/w600_and_h900_bestv2/uJXjZ3OgU8v0HKUPbHk1DZUW3m9.jpg",
          "duracao": null,
          "descricao": "Uma pequena cidade nota estranhas mortes no deserto. Há minhocas gigantes sob a areia. Eles podem ouvir a localização das pessoas através da vibração de seu movimento. Finalmente, eles os explodem com dinamite."
        },
        {
          "id": "ep-11092608",
          "tipo": "episodio",
          "titulo": "Palpitacoes - Carpinti [L] S01E05",
          "numero": 5,
          "temporada": 1,
          "xtreamId": "11092608",
          "container": "mp4",
          "capa": "https://image.tmdb.org/t/p/w600_and_h900_bestv2/uJXjZ3OgU8v0HKUPbHk1DZUW3m9.jpg",
          "duracao": null,
          "descricao": "Uma pequena cidade nota estranhas mortes no deserto. Há minhocas gigantes sob a areia. Eles podem ouvir a localização das pessoas através da vibração de seu movimento. Finalmente, eles os explodem com dinamite."
        },
        {
          "id": "ep-11092609",
          "tipo": "episodio",
          "titulo": "Palpitacoes - Carpinti [L] S01E06",
          "numero": 6,
          "temporada": 1,
          "xtreamId": "11092609",
          "container": "mp4",
          "capa": "https://image.tmdb.org/t/p/w600_and_h900_bestv2/uJXjZ3OgU8v0HKUPbHk1DZUW3m9.jpg",
          "duracao": null,
          "descricao": "Uma pequena cidade nota estranhas mortes no deserto. Há minhocas gigantes sob a areia. Eles podem ouvir a localização das pessoas através da vibração de seu movimento. Finalmente, eles os explodem com dinamite."
        },
        {
          "id": "ep-11092610",
          "tipo": "episodio",
          "titulo": "Palpitacoes - Carpinti [L] S01E07",
          "numero": 7,
          "temporada": 1,
          "xtreamId": "11092610",
          "container": "mp4",
          "capa": "https://image.tmdb.org/t/p/w600_and_h900_bestv2/uJXjZ3OgU8v0HKUPbHk1DZUW3m9.jpg",
          "duracao": null,
          "descricao": "Uma pequena cidade nota estranhas mortes no deserto. Há minhocas gigantes sob a areia. Eles podem ouvir a localização das pessoas através da vibração de seu movimento. Finalmente, eles os explodem com dinamite."
        },
        {
          "id": "ep-11092611",
          "tipo": "episodio",
          "titulo": "Palpitacoes - Carpinti [L] S01E08",
          "numero": 8,
          "temporada": 1,
          "xtreamId": "11092611",
          "container": "mp4",
          "capa": "https://image.tmdb.org/t/p/w600_and_h900_bestv2/uJXjZ3OgU8v0HKUPbHk1DZUW3m9.jpg",
          "duracao": null,
          "descricao": "Uma pequena cidade nota estranhas mortes no deserto. Há minhocas gigantes sob a areia. Eles podem ouvir a localização das pessoas através da vibração de seu movimento. Finalmente, eles os explodem com dinamite."
        },
        {
          "id": "ep-11092612",
          "tipo": "episodio",
          "titulo": "Palpitacoes - Carpinti [L] S01E09",
          "numero": 9,
          "temporada": 1,
          "xtreamId": "11092612",
          "container": "mp4",
          "capa": "https://image.tmdb.org/t/p/w600_and_h900_bestv2/uJXjZ3OgU8v0HKUPbHk1DZUW3m9.jpg",
          "duracao": null,
          "descricao": "Uma pequena cidade nota estranhas mortes no deserto. Há minhocas gigantes sob a areia. Eles podem ouvir a localização das pessoas através da vibração de seu movimento. Finalmente, eles os explodem com dinamite."
        },
        {
          "id": "ep-11092613",
          "tipo": "episodio",
          "titulo": "Palpitacoes - Carpinti [L] S01E10",
          "numero": 10,
          "temporada": 1,
          "xtreamId": "11092613",
          "container": "mp4",
          "capa": "https://image.tmdb.org/t/p/w600_and_h900_bestv2/uJXjZ3OgU8v0HKUPbHk1DZUW3m9.jpg",
          "duracao": null,
          "descricao": "Uma pequena cidade nota estranhas mortes no deserto. Há minhocas gigantes sob a areia. Eles podem ouvir a localização das pessoas através da vibração de seu movimento. Finalmente, eles os explodem com dinamite."
        },
        {
          "id": "ep-11092614",
          "tipo": "episodio",
          "titulo": "Palpitacoes - Carpinti [L] S01E11",
          "numero": 11,
          "temporada": 1,
          "xtreamId": "11092614",
          "container": "mp4",
          "capa": "https://image.tmdb.org/t/p/w600_and_h900_bestv2/uJXjZ3OgU8v0HKUPbHk1DZUW3m9.jpg",
          "duracao": null,
          "descricao": "Uma pequena cidade nota estranhas mortes no deserto. Há minhocas gigantes sob a areia. Eles podem ouvir a localização das pessoas através da vibração de seu movimento. Finalmente, eles os explodem com dinamite."
        },
        {
          "id": "ep-11092615",
          "tipo": "episodio",
          "titulo": "Palpitacoes - Carpinti [L] S01E12",
          "numero": 12,
          "temporada": 1,
          "xtreamId": "11092615",
          "container": "mp4",
          "capa": "https://image.tmdb.org/t/p/w600_and_h900_bestv2/uJXjZ3OgU8v0HKUPbHk1DZUW3m9.jpg",
          "duracao": null,
          "descricao": "Uma pequena cidade nota estranhas mortes no deserto. Há minhocas gigantes sob a areia. Eles podem ouvir a localização das pessoas através da vibração de seu movimento. Finalmente, eles os explodem com dinamite."
        },
        {
          "id": "ep-11092616",
          "tipo": "episodio",
          "titulo": "Palpitacoes - Carpinti [L] S01E13",
          "numero": 13,
          "temporada": 1,
          "xtreamId": "11092616",
          "container": "mp4",
          "capa": "https://image.tmdb.org/t/p/w600_and_h900_bestv2/uJXjZ3OgU8v0HKUPbHk1DZUW3m9.jpg",
          "duracao": null,
          "descricao": "Uma pequena cidade nota estranhas mortes no deserto. Há minhocas gigantes sob a areia. Eles podem ouvir a localização das pessoas através da vibração de seu movimento. Finalmente, eles os explodem com dinamite."
        }
      ]
    }
  ],
  "totalTemporadas": 1,
  "totalEpisodios": 13
}