{
  "id": "reacao-reaksiyon",
  "tipo": "serie",
  "titulo": "Reacao - Reaksiyon",
  "ano": null,
  "descricao": "Pessoas que viram de perto o acidente na usina nuclear Three Mile Island, na Pensilvânia, explicam os eventos, as controvérsias e as consequências que duram até hoje.",
  "generos": [
    "TURCAS | MEXICANAS"
  ],
  "capa": "https://image.tmdb.org/t/p/w600_and_h900_bestv2/6JGixD9P7hOhHBfiTpAdzWcpCxV.jpg",
  "banner": "https://image.tmdb.org/t/p/original/bQhaniCnd6PeS0u158UAOiyYmFO.jpg",
  "tmdbId": null,
  "nota": 7,
  "xtreamSeriesId": 8112,
  "temporadas": [
    {
      "numero": 1,
      "nome": "Temporada 1",
      "episodios": [
        {
          "id": "ep-11093721",
          "tipo": "episodio",
          "titulo": "Reacao - Reaksiyon [L] S01E01",
          "numero": 1,
          "temporada": 1,
          "xtreamId": "11093721",
          "container": "mp4",
          "capa": "https://image.tmdb.org/t/p/w600_and_h900_bestv2/6JGixD9P7hOhHBfiTpAdzWcpCxV.jpg",
          "duracao": null,
          "descricao": "Pessoas que viram de perto o acidente na usina nuclear Three Mile Island, na Pensilvânia, explicam os eventos, as controvérsias e as consequências que duram até hoje."
        },
        {
          "id": "ep-11093722",
          "tipo": "episodio",
          "titulo": "Reacao - Reaksiyon [L] S01E02",
          "numero": 2,
          "temporada": 1,
          "xtreamId": "11093722",
          "container": "mp4",
          "capa": "https://image.tmdb.org/t/p/w600_and_h900_bestv2/6JGixD9P7hOhHBfiTpAdzWcpCxV.jpg",
          "duracao": null,
          "descricao": "Pessoas que viram de perto o acidente na usina nuclear Three Mile Island, na Pensilvânia, explicam os eventos, as controvérsias e as consequências que duram até hoje."
        },
        {
          "id": "ep-11093723",
          "tipo": "episodio",
          "titulo": "Reacao - Reaksiyon [L] S01E03",
          "numero": 3,
          "temporada": 1,
          "xtreamId": "11093723",
          "container": "mp4",
          "capa": "https://image.tmdb.org/t/p/w600_and_h900_bestv2/6JGixD9P7hOhHBfiTpAdzWcpCxV.jpg",
          "duracao": null,
          "descricao": "Pessoas que viram de perto o acidente na usina nuclear Three Mile Island, na Pensilvânia, explicam os eventos, as controvérsias e as consequências que duram até hoje."
        },
        {
          "id": "ep-11093724",
          "tipo": "episodio",
          "titulo": "Reacao - Reaksiyon [L] S01E04",
          "numero": 4,
          "temporada": 1,
          "xtreamId": "11093724",
          "container": "mp4",
          "capa": "https://image.tmdb.org/t/p/w600_and_h900_bestv2/6JGixD9P7hOhHBfiTpAdzWcpCxV.jpg",
          "duracao": null,
          "descricao": "Pessoas que viram de perto o acidente na usina nuclear Three Mile Island, na Pensilvânia, explicam os eventos, as controvérsias e as consequências que duram até hoje."
        },
        {
          "id": "ep-11093725",
          "tipo": "episodio",
          "titulo": "Reacao - Reaksiyon [L] S01E05",
          "numero": 5,
          "temporada": 1,
          "xtreamId": "11093725",
          "container": "mp4",
          "capa": "https://image.tmdb.org/t/p/w600_and_h900_bestv2/6JGixD9P7hOhHBfiTpAdzWcpCxV.jpg",
          "duracao": null,
          "descricao": "Pessoas que viram de perto o acidente na usina nuclear Three Mile Island, na Pensilvânia, explicam os eventos, as controvérsias e as consequências que duram até hoje."
        },
        {
          "id": "ep-11093726",
          "tipo": "episodio",
          "titulo": "Reacao - Reaksiyon [L] S01E06",
          "numero": 6,
          "temporada": 1,
          "xtreamId": "11093726",
          "container": "mp4",
          "capa": "https://image.tmdb.org/t/p/w600_and_h900_bestv2/6JGixD9P7hOhHBfiTpAdzWcpCxV.jpg",
          "duracao": null,
          "descricao": "Pessoas que viram de perto o acidente na usina nuclear Three Mile Island, na Pensilvânia, explicam os eventos, as controvérsias e as consequências que duram até hoje."
        },
        {
          "id": "ep-11093727",
          "tipo": "episodio",
          "titulo": "Reacao - Reaksiyon [L] S01E07",
          "numero": 7,
          "temporada": 1,
          "xtreamId": "11093727",
          "container": "mp4",
          "capa": "https://image.tmdb.org/t/p/w600_and_h900_bestv2/6JGixD9P7hOhHBfiTpAdzWcpCxV.jpg",
          "duracao": null,
          "descricao": "Pessoas que viram de perto o acidente na usina nuclear Three Mile Island, na Pensilvânia, explicam os eventos, as controvérsias e as consequências que duram até hoje."
        },
        {
          "id": "ep-11093728",
          "tipo": "episodio",
          "titulo": "Reacao - Reaksiyon [L] S01E08",
          "numero": 8,
          "temporada": 1,
          "xtreamId": "11093728",
          "container": "mp4",
          "capa": "https://image.tmdb.org/t/p/w600_and_h900_bestv2/6JGixD9P7hOhHBfiTpAdzWcpCxV.jpg",
          "duracao": null,
          "descricao": "Pessoas que viram de perto o acidente na usina nuclear Three Mile Island, na Pensilvânia, explicam os eventos, as controvérsias e as consequências que duram até hoje."
        },
        {
          "id": "ep-11093729",
          "tipo": "episodio",
          "titulo": "Reacao - Reaksiyon [L] S01E09",
          "numero": 9,
          "temporada": 1,
          "xtreamId": "11093729",
          "container": "mp4",
          "capa": "https://image.tmdb.org/t/p/w600_and_h900_bestv2/6JGixD9P7hOhHBfiTpAdzWcpCxV.jpg",
          "duracao": null,
          "descricao": "Pessoas que viram de perto o acidente na usina nuclear Three Mile Island, na Pensilvânia, explicam os eventos, as controvérsias e as consequências que duram até hoje."
        },
        {
          "id": "ep-11093730",
          "tipo": "episodio",
          "titulo": "Reacao - Reaksiyon [L] S01E10",
          "numero": 10,
          "temporada": 1,
          "xtreamId": "11093730",
          "container": "mp4",
          "capa": "https://image.tmdb.org/t/p/w600_and_h900_bestv2/6JGixD9P7hOhHBfiTpAdzWcpCxV.jpg",
          "duracao": null,
          "descricao": "Pessoas que viram de perto o acidente na usina nuclear Three Mile Island, na Pensilvânia, explicam os eventos, as controvérsias e as consequências que duram até hoje."
        },
        {
          "id": "ep-11093731",
          "tipo": "episodio",
          "titulo": "Reacao - Reaksiyon [L] S01E11",
          "numero": 11,
          "temporada": 1,
          "xtreamId": "11093731",
          "container": "mp4",
          "capa": "https://image.tmdb.org/t/p/w600_and_h900_bestv2/6JGixD9P7hOhHBfiTpAdzWcpCxV.jpg",
          "duracao": null,
          "descricao": "Pessoas que viram de perto o acidente na usina nuclear Three Mile Island, na Pensilvânia, explicam os eventos, as controvérsias e as consequências que duram até hoje."
        },
        {
          "id": "ep-11093732",
          "tipo": "episodio",
          "titulo": "Reacao - Reaksiyon [L] S01E12",
          "numero": 12,
          "temporada": 1,
          "xtreamId": "11093732",
          "container": "mp4",
          "capa": "https://image.tmdb.org/t/p/w600_and_h900_bestv2/6JGixD9P7hOhHBfiTpAdzWcpCxV.jpg",
          "duracao": null,
          "descricao": "Pessoas que viram de perto o acidente na usina nuclear Three Mile Island, na Pensilvânia, explicam os eventos, as controvérsias e as consequências que duram até hoje."
        },
        {
          "id": "ep-11093733",
          "tipo": "episodio",
          "titulo": "Reacao - Reaksiyon [L] S01E13",
          "numero": 13,
          "temporada": 1,
          "xtreamId": "11093733",
          "container": "mp4",
          "capa": "https://image.tmdb.org/t/p/w600_and_h900_bestv2/6JGixD9P7hOhHBfiTpAdzWcpCxV.jpg",
          "duracao": null,
          "descricao": "Pessoas que viram de perto o acidente na usina nuclear Three Mile Island, na Pensilvânia, explicam os eventos, as controvérsias e as consequências que duram até hoje."
        }
      ]
    }
  ],
  "totalTemporadas": 1,
  "totalEpisodios": 13
}