{
  "id": "seculo-magnifico-kosem-muhtesem-yuzy-l-kosem",
  "tipo": "serie",
  "titulo": "Seculo Magnifico Kosem - Muhteşem Yüzyıl Kösem",
  "ano": null,
  "descricao": "",
  "generos": [
    "TURCAS | MEXICANAS"
  ],
  "capa": null,
  "tmdbId": null,
  "nota": 0,
  "xtreamSeriesId": 8133,
  "temporadas": [
    {
      "numero": 1,
      "nome": "Temporada 1",
      "episodios": [
        {
          "id": "ep-11094751",
          "tipo": "episodio",
          "titulo": "Seculo Magnifico Kosem - Muhteşem Yüzyıl Kösem [L] S01E01",
          "numero": 1,
          "temporada": 1,
          "xtreamId": "11094751",
          "container": "mp4",
          "capa": null,
          "duracao": null,
          "descricao": ""
        },
        {
          "id": "ep-11094752",
          "tipo": "episodio",
          "titulo": "Seculo Magnifico Kosem - Muhteşem Yüzyıl Kösem [L] S01E02",
          "numero": 2,
          "temporada": 1,
          "xtreamId": "11094752",
          "container": "mp4",
          "capa": null,
          "duracao": null,
          "descricao": ""
        },
        {
          "id": "ep-11094753",
          "tipo": "episodio",
          "titulo": "Seculo Magnifico Kosem - Muhteşem Yüzyıl Kösem [L] S01E03",
          "numero": 3,
          "temporada": 1,
          "xtreamId": "11094753",
          "container": "mp4",
          "capa": null,
          "duracao": null,
          "descricao": ""
        },
        {
          "id": "ep-11094754",
          "tipo": "episodio",
          "titulo": "Seculo Magnifico Kosem - Muhteşem Yüzyıl Kösem [L] S01E04",
          "numero": 4,
          "temporada": 1,
          "xtreamId": "11094754",
          "container": "mp4",
          "capa": null,
          "duracao": null,
          "descricao": ""
        },
        {
          "id": "ep-11094755",
          "tipo": "episodio",
          "titulo": "Seculo Magnifico Kosem - Muhteşem Yüzyıl Kösem [L] S01E05",
          "numero": 5,
          "temporada": 1,
          "xtreamId": "11094755",
          "container": "mp4",
          "capa": null,
          "duracao": null,
          "descricao": ""
        },
        {
          "id": "ep-11094756",
          "tipo": "episodio",
          "titulo": "Seculo Magnifico Kosem - Muhteşem Yüzyıl Kösem [L] S01E06",
          "numero": 6,
          "temporada": 1,
          "xtreamId": "11094756",
          "container": "mp4",
          "capa": null,
          "duracao": null,
          "descricao": ""
        },
        {
          "id": "ep-11094757",
          "tipo": "episodio",
          "titulo": "Seculo Magnifico Kosem - Muhteşem Yüzyıl Kösem [L] S01E07",
          "numero": 7,
          "temporada": 1,
          "xtreamId": "11094757",
          "container": "mp4",
          "capa": null,
          "duracao": null,
          "descricao": ""
        },
        {
          "id": "ep-11094758",
          "tipo": "episodio",
          "titulo": "Seculo Magnifico Kosem - Muhteşem Yüzyıl Kösem [L] S01E08",
          "numero": 8,
          "temporada": 1,
          "xtreamId": "11094758",
          "container": "mp4",
          "capa": null,
          "duracao": null,
          "descricao": ""
        },
        {
          "id": "ep-11094759",
          "tipo": "episodio",
          "titulo": "Seculo Magnifico Kosem - Muhteşem Yüzyıl Kösem [L] S01E09",
          "numero": 9,
          "temporada": 1,
          "xtreamId": "11094759",
          "container": "mp4",
          "capa": null,
          "duracao": null,
          "descricao": ""
        },
        {
          "id": "ep-11094760",
          "tipo": "episodio",
          "titulo": "Seculo Magnifico Kosem - Muhteşem Yüzyıl Kösem [L] S01E10",
          "numero": 10,
          "temporada": 1,
          "xtreamId": "11094760",
          "container": "mp4",
          "capa": null,
          "duracao": null,
          "descricao": ""
        },
        {
          "id": "ep-11094761",
          "tipo": "episodio",
          "titulo": "Seculo Magnifico Kosem - Muhteşem Yüzyıl Kösem [L] S01E11",
          "numero": 11,
          "temporada": 1,
          "xtreamId": "11094761",
          "container": "mp4",
          "capa": null,
          "duracao": null,
          "descricao": ""
        },
        {
          "id": "ep-11094762",
          "tipo": "episodio",
          "titulo": "Seculo Magnifico Kosem - Muhteşem Yüzyıl Kösem [L] S01E12",
          "numero": 12,
          "temporada": 1,
          "xtreamId": "11094762",
          "container": "mp4",
          "capa": null,
          "duracao": null,
          "descricao": ""
        },
        {
          "id": "ep-11094763",
          "tipo": "episodio",
          "titulo": "Seculo Magnifico Kosem - Muhteşem Yüzyıl Kösem [L] S01E13",
          "numero": 13,
          "temporada": 1,
          "xtreamId": "11094763",
          "container": "mp4",
          "capa": null,
          "duracao": null,
          "descricao": ""
        },
        {
          "id": "ep-11094764",
          "tipo": "episodio",
          "titulo": "Seculo Magnifico Kosem - Muhteşem Yüzyıl Kösem [L] S01E14",
          "numero": 14,
          "temporada": 1,
          "xtreamId": "11094764",
          "container": "mp4",
          "capa": null,
          "duracao": null,
          "descricao": ""
        },
        {
          "id": "ep-11094765",
          "tipo": "episodio",
          "titulo": "Seculo Magnifico Kosem - Muhteşem Yüzyıl Kösem [L] S01E15",
          "numero": 15,
          "temporada": 1,
          "xtreamId": "11094765",
          "container": "mp4",
          "capa": null,
          "duracao": null,
          "descricao": ""
        },
        {
          "id": "ep-11094766",
          "tipo": "episodio",
          "titulo": "Seculo Magnifico Kosem - Muhteşem Yüzyıl Kösem [L] S01E16",
          "numero": 16,
          "temporada": 1,
          "xtreamId": "11094766",
          "container": "mp4",
          "capa": null,
          "duracao": null,
          "descricao": ""
        },
        {
          "id": "ep-11094767",
          "tipo": "episodio",
          "titulo": "Seculo Magnifico Kosem - Muhteşem Yüzyıl Kösem [L] S01E17",
          "numero": 17,
          "temporada": 1,
          "xtreamId": "11094767",
          "container": "mp4",
          "capa": null,
          "duracao": null,
          "descricao": ""
        },
        {
          "id": "ep-11094768",
          "tipo": "episodio",
          "titulo": "Seculo Magnifico Kosem - Muhteşem Yüzyıl Kösem [L] S01E18",
          "numero": 18,
          "temporada": 1,
          "xtreamId": "11094768",
          "container": "mp4",
          "capa": null,
          "duracao": null,
          "descricao": ""
        },
        {
          "id": "ep-11094769",
          "tipo": "episodio",
          "titulo": "Seculo Magnifico Kosem - Muhteşem Yüzyıl Kösem [L] S01E19",
          "numero": 19,
          "temporada": 1,
          "xtreamId": "11094769",
          "container": "mp4",
          "capa": null,
          "duracao": null,
          "descricao": ""
        },
        {
          "id": "ep-11094770",
          "tipo": "episodio",
          "titulo": "Seculo Magnifico Kosem - Muhteşem Yüzyıl Kösem [L] S01E20",
          "numero": 20,
          "temporada": 1,
          "xtreamId": "11094770",
          "container": "mp4",
          "capa": null,
          "duracao": null,
          "descricao": ""
        },
        {
          "id": "ep-11094771",
          "tipo": "episodio",
          "titulo": "Seculo Magnifico Kosem - Muhteşem Yüzyıl Kösem [L] S01E21",
          "numero": 21,
          "temporada": 1,
          "xtreamId": "11094771",
          "container": "mp4",
          "capa": null,
          "duracao": null,
          "descricao": ""
        },
        {
          "id": "ep-11094772",
          "tipo": "episodio",
          "titulo": "Seculo Magnifico Kosem - Muhteşem Yüzyıl Kösem [L] S01E22",
          "numero": 22,
          "temporada": 1,
          "xtreamId": "11094772",
          "container": "mp4",
          "capa": null,
          "duracao": null,
          "descricao": ""
        },
        {
          "id": "ep-11094773",
          "tipo": "episodio",
          "titulo": "Seculo Magnifico Kosem - Muhteşem Yüzyıl Kösem [L] S01E23",
          "numero": 23,
          "temporada": 1,
          "xtreamId": "11094773",
          "container": "mp4",
          "capa": null,
          "duracao": null,
          "descricao": ""
        },
        {
          "id": "ep-11094774",
          "tipo": "episodio",
          "titulo": "Seculo Magnifico Kosem - Muhteşem Yüzyıl Kösem [L] S01E24",
          "numero": 24,
          "temporada": 1,
          "xtreamId": "11094774",
          "container": "mp4",
          "capa": null,
          "duracao": null,
          "descricao": ""
        },
        {
          "id": "ep-11094775",
          "tipo": "episodio",
          "titulo": "Seculo Magnifico Kosem - Muhteşem Yüzyıl Kösem [L] S01E25",
          "numero": 25,
          "temporada": 1,
          "xtreamId": "11094775",
          "container": "mp4",
          "capa": null,
          "duracao": null,
          "descricao": ""
        },
        {
          "id": "ep-11094776",
          "tipo": "episodio",
          "titulo": "Seculo Magnifico Kosem - Muhteşem Yüzyıl Kösem [L] S01E26",
          "numero": 26,
          "temporada": 1,
          "xtreamId": "11094776",
          "container": "mp4",
          "capa": null,
          "duracao": null,
          "descricao": ""
        },
        {
          "id": "ep-11094777",
          "tipo": "episodio",
          "titulo": "Seculo Magnifico Kosem - Muhteşem Yüzyıl Kösem [L] S01E27",
          "numero": 27,
          "temporada": 1,
          "xtreamId": "11094777",
          "container": "mp4",
          "capa": null,
          "duracao": null,
          "descricao": ""
        },
        {
          "id": "ep-11094778",
          "tipo": "episodio",
          "titulo": "Seculo Magnifico Kosem - Muhteşem Yüzyıl Kösem [L] S01E28",
          "numero": 28,
          "temporada": 1,
          "xtreamId": "11094778",
          "container": "mp4",
          "capa": null,
          "duracao": null,
          "descricao": ""
        },
        {
          "id": "ep-11094779",
          "tipo": "episodio",
          "titulo": "Seculo Magnifico Kosem - Muhteşem Yüzyıl Kösem [L] S01E29",
          "numero": 29,
          "temporada": 1,
          "xtreamId": "11094779",
          "container": "mp4",
          "capa": null,
          "duracao": null,
          "descricao": ""
        },
        {
          "id": "ep-11094780",
          "tipo": "episodio",
          "titulo": "Seculo Magnifico Kosem - Muhteşem Yüzyıl Kösem [L] S01E30",
          "numero": 30,
          "temporada": 1,
          "xtreamId": "11094780",
          "container": "mp4",
          "capa": null,
          "duracao": null,
          "descricao": ""
        },
        {
          "id": "ep-11094781",
          "tipo": "episodio",
          "titulo": "Seculo Magnifico Kosem - Muhteşem Yüzyıl Kösem [L] S01E31",
          "numero": 31,
          "temporada": 1,
          "xtreamId": "11094781",
          "container": "mp4",
          "capa": null,
          "duracao": null,
          "descricao": ""
        },
        {
          "id": "ep-11094782",
          "tipo": "episodio",
          "titulo": "Seculo Magnifico Kosem - Muhteşem Yüzyıl Kösem [L] S01E32",
          "numero": 32,
          "temporada": 1,
          "xtreamId": "11094782",
          "container": "mp4",
          "capa": null,
          "duracao": null,
          "descricao": ""
        },
        {
          "id": "ep-11094783",
          "tipo": "episodio",
          "titulo": "Seculo Magnifico Kosem - Muhteşem Yüzyıl Kösem [L] S01E33",
          "numero": 33,
          "temporada": 1,
          "xtreamId": "11094783",
          "container": "mp4",
          "capa": null,
          "duracao": null,
          "descricao": ""
        },
        {
          "id": "ep-11094784",
          "tipo": "episodio",
          "titulo": "Seculo Magnifico Kosem - Muhteşem Yüzyıl Kösem [L] S01E34",
          "numero": 34,
          "temporada": 1,
          "xtreamId": "11094784",
          "container": "mp4",
          "capa": null,
          "duracao": null,
          "descricao": ""
        },
        {
          "id": "ep-11094785",
          "tipo": "episodio",
          "titulo": "Seculo Magnifico Kosem - Muhteşem Yüzyıl Kösem [L] S01E35",
          "numero": 35,
          "temporada": 1,
          "xtreamId": "11094785",
          "container": "mp4",
          "capa": null,
          "duracao": null,
          "descricao": ""
        },
        {
          "id": "ep-11094786",
          "tipo": "episodio",
          "titulo": "Seculo Magnifico Kosem - Muhteşem Yüzyıl Kösem [L] S01E36",
          "numero": 36,
          "temporada": 1,
          "xtreamId": "11094786",
          "container": "mp4",
          "capa": null,
          "duracao": null,
          "descricao": ""
        },
        {
          "id": "ep-11094787",
          "tipo": "episodio",
          "titulo": "Seculo Magnifico Kosem - Muhteşem Yüzyıl Kösem [L] S01E37",
          "numero": 37,
          "temporada": 1,
          "xtreamId": "11094787",
          "container": "mp4",
          "capa": null,
          "duracao": null,
          "descricao": ""
        },
        {
          "id": "ep-11094788",
          "tipo": "episodio",
          "titulo": "Seculo Magnifico Kosem - Muhteşem Yüzyıl Kösem [L] S01E38",
          "numero": 38,
          "temporada": 1,
          "xtreamId": "11094788",
          "container": "mp4",
          "capa": null,
          "duracao": null,
          "descricao": ""
        },
        {
          "id": "ep-11094789",
          "tipo": "episodio",
          "titulo": "Seculo Magnifico Kosem - Muhteşem Yüzyıl Kösem [L] S01E39",
          "numero": 39,
          "temporada": 1,
          "xtreamId": "11094789",
          "container": "mp4",
          "capa": null,
          "duracao": null,
          "descricao": ""
        },
        {
          "id": "ep-11094790",
          "tipo": "episodio",
          "titulo": "Seculo Magnifico Kosem - Muhteşem Yüzyıl Kösem [L] S01E40",
          "numero": 40,
          "temporada": 1,
          "xtreamId": "11094790",
          "container": "mp4",
          "capa": null,
          "duracao": null,
          "descricao": ""
        },
        {
          "id": "ep-11094791",
          "tipo": "episodio",
          "titulo": "Seculo Magnifico Kosem - Muhteşem Yüzyıl Kösem [L] S01E41",
          "numero": 41,
          "temporada": 1,
          "xtreamId": "11094791",
          "container": "mp4",
          "capa": null,
          "duracao": null,
          "descricao": ""
        },
        {
          "id": "ep-11094792",
          "tipo": "episodio",
          "titulo": "Seculo Magnifico Kosem - Muhteşem Yüzyıl Kösem [L] S01E42",
          "numero": 42,
          "temporada": 1,
          "xtreamId": "11094792",
          "container": "mp4",
          "capa": null,
          "duracao": null,
          "descricao": ""
        },
        {
          "id": "ep-11094793",
          "tipo": "episodio",
          "titulo": "Seculo Magnifico Kosem - Muhteşem Yüzyıl Kösem [L] S01E43",
          "numero": 43,
          "temporada": 1,
          "xtreamId": "11094793",
          "container": "mp4",
          "capa": null,
          "duracao": null,
          "descricao": ""
        },
        {
          "id": "ep-11094794",
          "tipo": "episodio",
          "titulo": "Seculo Magnifico Kosem - Muhteşem Yüzyıl Kösem [L] S01E44",
          "numero": 44,
          "temporada": 1,
          "xtreamId": "11094794",
          "container": "mp4",
          "capa": null,
          "duracao": null,
          "descricao": ""
        },
        {
          "id": "ep-11094795",
          "tipo": "episodio",
          "titulo": "Seculo Magnifico Kosem - Muhteşem Yüzyıl Kösem [L] S01E45",
          "numero": 45,
          "temporada": 1,
          "xtreamId": "11094795",
          "container": "mp4",
          "capa": null,
          "duracao": null,
          "descricao": ""
        },
        {
          "id": "ep-11094796",
          "tipo": "episodio",
          "titulo": "Seculo Magnifico Kosem - Muhteşem Yüzyıl Kösem [L] S01E46",
          "numero": 46,
          "temporada": 1,
          "xtreamId": "11094796",
          "container": "mp4",
          "capa": null,
          "duracao": null,
          "descricao": ""
        },
        {
          "id": "ep-11094797",
          "tipo": "episodio",
          "titulo": "Seculo Magnifico Kosem - Muhteşem Yüzyıl Kösem [L] S01E47",
          "numero": 47,
          "temporada": 1,
          "xtreamId": "11094797",
          "container": "mp4",
          "capa": null,
          "duracao": null,
          "descricao": ""
        },
        {
          "id": "ep-11094798",
          "tipo": "episodio",
          "titulo": "Seculo Magnifico Kosem - Muhteşem Yüzyıl Kösem [L] S01E48",
          "numero": 48,
          "temporada": 1,
          "xtreamId": "11094798",
          "container": "mp4",
          "capa": null,
          "duracao": null,
          "descricao": ""
        },
        {
          "id": "ep-11094799",
          "tipo": "episodio",
          "titulo": "Seculo Magnifico Kosem - Muhteşem Yüzyıl Kösem [L] S01E49",
          "numero": 49,
          "temporada": 1,
          "xtreamId": "11094799",
          "container": "mp4",
          "capa": null,
          "duracao": null,
          "descricao": ""
        },
        {
          "id": "ep-11094800",
          "tipo": "episodio",
          "titulo": "Seculo Magnifico Kosem - Muhteşem Yüzyıl Kösem [L] S01E50",
          "numero": 50,
          "temporada": 1,
          "xtreamId": "11094800",
          "container": "mp4",
          "capa": null,
          "duracao": null,
          "descricao": ""
        },
        {
          "id": "ep-11094801",
          "tipo": "episodio",
          "titulo": "Seculo Magnifico Kosem - Muhteşem Yüzyıl Kösem [L] S01E51",
          "numero": 51,
          "temporada": 1,
          "xtreamId": "11094801",
          "container": "mp4",
          "capa": null,
          "duracao": null,
          "descricao": ""
        },
        {
          "id": "ep-11094802",
          "tipo": "episodio",
          "titulo": "Seculo Magnifico Kosem - Muhteşem Yüzyıl Kösem [L] S01E52",
          "numero": 52,
          "temporada": 1,
          "xtreamId": "11094802",
          "container": "mp4",
          "capa": null,
          "duracao": null,
          "descricao": ""
        },
        {
          "id": "ep-11094803",
          "tipo": "episodio",
          "titulo": "Seculo Magnifico Kosem - Muhteşem Yüzyıl Kösem [L] S01E53",
          "numero": 53,
          "temporada": 1,
          "xtreamId": "11094803",
          "container": "mp4",
          "capa": null,
          "duracao": null,
          "descricao": ""
        },
        {
          "id": "ep-11094804",
          "tipo": "episodio",
          "titulo": "Seculo Magnifico Kosem - Muhteşem Yüzyıl Kösem [L] S01E54",
          "numero": 54,
          "temporada": 1,
          "xtreamId": "11094804",
          "container": "mp4",
          "capa": null,
          "duracao": null,
          "descricao": ""
        },
        {
          "id": "ep-11094805",
          "tipo": "episodio",
          "titulo": "Seculo Magnifico Kosem - Muhteşem Yüzyıl Kösem [L] S01E55",
          "numero": 55,
          "temporada": 1,
          "xtreamId": "11094805",
          "container": "mp4",
          "capa": null,
          "duracao": null,
          "descricao": ""
        },
        {
          "id": "ep-11094806",
          "tipo": "episodio",
          "titulo": "Seculo Magnifico Kosem - Muhteşem Yüzyıl Kösem [L] S01E56",
          "numero": 56,
          "temporada": 1,
          "xtreamId": "11094806",
          "container": "mp4",
          "capa": null,
          "duracao": null,
          "descricao": ""
        },
        {
          "id": "ep-11094807",
          "tipo": "episodio",
          "titulo": "Seculo Magnifico Kosem - Muhteşem Yüzyıl Kösem [L] S01E57",
          "numero": 57,
          "temporada": 1,
          "xtreamId": "11094807",
          "container": "mp4",
          "capa": null,
          "duracao": null,
          "descricao": ""
        },
        {
          "id": "ep-11094808",
          "tipo": "episodio",
          "titulo": "Seculo Magnifico Kosem - Muhteşem Yüzyıl Kösem [L] S01E58",
          "numero": 58,
          "temporada": 1,
          "xtreamId": "11094808",
          "container": "mp4",
          "capa": null,
          "duracao": null,
          "descricao": ""
        },
        {
          "id": "ep-11094809",
          "tipo": "episodio",
          "titulo": "Seculo Magnifico Kosem - Muhteşem Yüzyıl Kösem [L] S01E59",
          "numero": 59,
          "temporada": 1,
          "xtreamId": "11094809",
          "container": "mp4",
          "capa": null,
          "duracao": null,
          "descricao": ""
        },
        {
          "id": "ep-11094810",
          "tipo": "episodio",
          "titulo": "Seculo Magnifico Kosem - Muhteşem Yüzyıl Kösem [L] S01E60",
          "numero": 60,
          "temporada": 1,
          "xtreamId": "11094810",
          "container": "mp4",
          "capa": null,
          "duracao": null,
          "descricao": ""
        }
      ]
    }
  ],
  "totalTemporadas": 1,
  "totalEpisodios": 60
}